Workbook

Sheet INGRESOS
A1: FECHA | B1: DIA | C1: MES | D1: ANIO | E1: TIPO_DIA | F1: NUM_SEM | G1: QNA | H1: MONTO | I1: BANCO | J1: CONCEPTO | K1: COMENTARIOS | L1: SALDO ACUM | M1: RECAT | N1: AGRUPACION | O1: INDICE
A2: 45507 | B2: =DAY(A2) -> 3 | C2: =MONTH(A2) -> 8 | D2: =YEAR(A2) -> 2024 | E2: =WEEKDAY(A2,2) -> 6 | F2: =WEEKNUM(A2,2) - WEEKNUM(DATE(YEAR(A2),MONTH(A2),1),2) + 1 -> 1 | H2: 277 | I2: BBVA | M2: NO DATO | N2: NO DATO | O2: NO DATO
A3: 45519 | B3: =DAY(A3) -> 15 | C3: =MONTH(A3) -> 8 | D3: =YEAR(A3) -> 2024 | E3: =WEEKDAY(A3,2) -> 4 | F3: =WEEKNUM(A3,2) - WEEKNUM(DATE(YEAR(A3),MONTH(A3),1),2) + 1 -> 3 | G3: 1 | H3: 729.22 | I3: BBVA | M3: NO DATO | N3: NO DATO | O3: NO DATO
A4: 45522 | B4: =DAY(A4) -> 18 | C4: =MONTH(A4) -> 8 | D4: =YEAR(A4) -> 2024 | E4: =WEEKDAY(A4,2) -> 7 | F4: =WEEKNUM(A4,2) - WEEKNUM(DATE(YEAR(A4),MONTH(A4),1),2) + 1 -> 3 | H4: 1856.11 | I4: BBVA | M4: NO DATO | N4: NO DATO | O4: NO DATO
A5: 45524 | B5: =DAY(A5) -> 20 | C5: =MONTH(A5) -> 8 | D5: =YEAR(A5) -> 2024 | E5: =WEEKDAY(A5,2) -> 2 | F5: =WEEKNUM(A5,2) - WEEKNUM(DATE(YEAR(A5),MONTH(A5),1),2) + 1 -> 4 | H5: 1043.51 | I5: BBVA | M5: NO DATO | N5: NO DATO | O5: NO DATO
A6: 45529 | B6: =DAY(A6) -> 25 | C6: =MONTH(A6) -> 8 | D6: =YEAR(A6) -> 2024 | E6: =WEEKDAY(A6,2) -> 7 | F6: =WEEKNUM(A6,2) - WEEKNUM(DATE(YEAR(A6),MONTH(A6),1),2) + 1 -> 4 | H6: 575.67 | I6: BBVA | M6: NO DATO | N6: NO DATO | O6: NO DATO
A7: 44968 | B7: =DAY(A7) -> 11 | C7: =MONTH(A7) -> 2 | D7: =YEAR(A7) -> 2023 | E7: =WEEKDAY(A7,2) -> 6 | F7: =WEEKNUM(A7,2) - WEEKNUM(DATE(YEAR(A7),MONTH(A7),1),2) + 1 -> 2 | H7: 1815 | I7: BBVA | J7: DONATIVO | M7: =VLOOKUP(J7,RECATALOGANDO!A:C,2,0) -> DONATIVO | N7: =VLOOKUP(M7,RECATALOGANDO!B:C,2,0) -> DONATIVO | O7: NO ES INGRESO
A8: 44968 | B8: =DAY(A8) -> 11 | C8: =MONTH(A8) -> 2 | D8: =YEAR(A8) -> 2023 | E8: =WEEKDAY(A8,2) -> 6 | F8: =WEEKNUM(A8,2) - WEEKNUM(DATE(YEAR(A8),MONTH(A8),1),2) + 1 -> 2 | H8: 1815 | I8: BBVA | J8: DONATIVO | M8: =VLOOKUP(J8,RECATALOGANDO!A:C,2,0) -> DONATIVO | N8: =VLOOKUP(M8,RECATALOGANDO!B:C,2,0) -> DONATIVO | O8: NO ES INGRESO
A9: 45118 | B9: =DAY(A9) -> 11 | C9: =MONTH(A9) -> 7 | D9: =YEAR(A9) -> 2023 | E9: =WEEKDAY(A9,2) -> 2 | F9: =WEEKNUM(A9,2) - WEEKNUM(DATE(YEAR(A9),MONTH(A9),1),2) + 1 -> 3 | H9: 55900 | I9: BBVA | J9: PRESTAMO BANCARIO | M9: =VLOOKUP(J9,RECATALOGANDO!A:C,2,0) -> PRESTAMO BANCARIO | N9: =VLOOKUP(M9,RECATALOGANDO!B:C,2,0) -> PRESTAMO | O9: NO ES INGRESO
A10: 45173 | B10: =DAY(A10) -> 4 | C10: =MONTH(A10) -> 9 | D10: =YEAR(A10) -> 2023 | E10: =WEEKDAY(A10,2) -> 1 | F10: =WEEKNUM(A10,2) - WEEKNUM(DATE(YEAR(A10),MONTH(A10),1),2) + 1 -> 2 | H10: 26571 | I10: BANAMEX | J10: DEPÓSITO EQUIVOCADO Y DEVUELTO | M10: =VLOOKUP(J10,RECATALOGANDO!A:C,2,0) -> REEMBOLSO | N10: =VLOOKUP(M10,RECATALOGANDO!B:C,2,0) -> DINERO DEVUELTO A ORIGEN | O10: NO ES INGRESO
A11: 45181 | B11: =DAY(A11) -> 12 | C11: =MONTH(A11) -> 9 | D11: =YEAR(A11) -> 2023 | E11: =WEEKDAY(A11,2) -> 2 | F11: =WEEKNUM(A11,2) - WEEKNUM(DATE(YEAR(A11),MONTH(A11),1),2) + 1 -> 3 | H11: 80000 | I11: BBVA | J11: DEPÓSITO PRESTAMO | M11: =VLOOKUP(J11,RECATALOGANDO!A:C,2,0) -> DEPÓSITO PRESTAMO | N11: =VLOOKUP(M11,RECATALOGANDO!B:C,2,0) -> PRESTAMO | O11: NO ES INGRESO
A12: 45215 | B12: =DAY(A12) -> 16 | C12: =MONTH(A12) -> 10 | D12: =YEAR(A12) -> 2023 | E12: =WEEKDAY(A12,2) -> 1 | F12: =WEEKNUM(A12,2) - WEEKNUM(DATE(YEAR(A12),MONTH(A12),1),2) + 1 -> 4 | H12: 200 | I12: BANAMEX | J12: REEMBOLSO | M12: =VLOOKUP(J12,RECATALOGANDO!A:C,2,0) -> REEMBOLSO | N12: =VLOOKUP(M12,RECATALOGANDO!B:C,2,0) -> DINERO DEVUELTO A ORIGEN | O12: NO ES INGRESO
A13: 45282 | B13: =DAY(A13) -> 22 | C13: =MONTH(A13) -> 12 | D13: =YEAR(A13) -> 2023 | E13: =WEEKDAY(A13,2) -> 5 | F13: =WEEKNUM(A13,2) - WEEKNUM(DATE(YEAR(A13),MONTH(A13),1),2) + 1 -> 4 | H13: 2895 | I13: BBVA | J13: REEMBOLSO POR DEPOSITO EQUIVOCADO | M13: =VLOOKUP(J13,RECATALOGANDO!A:C,2,0) -> REEMBOLSO | N13: =VLOOKUP(M13,RECATALOGANDO!B:C,2,0) -> DINERO DEVUELTO A ORIGEN | O13: NO ES INGRESO
A14: 45365 | B14: =DAY(A14) -> 14 | C14: =MONTH(A14) -> 3 | D14: =YEAR(A14) -> 2024 | E14: =WEEKDAY(A14,2) -> 4 | F14: =WEEKNUM(A14,2) - WEEKNUM(DATE(YEAR(A14),MONTH(A14),1),2) + 1 -> 3 | H14: 3500 | I14: BBVA | J14: REEMBOLSO | M14: =VLOOKUP(J14,RECATALOGANDO!A:C,2,0) -> REEMBOLSO | N14: =VLOOKUP(M14,RECATALOGANDO!B:C,2,0) -> DINERO DEVUELTO A ORIGEN | O14: NO ES INGRESO
A15: 45366 | B15: =DAY(A15) -> 15 | C15: =MONTH(A15) -> 3 | D15: =YEAR(A15) -> 2024 | E15: =WEEKDAY(A15,2) -> 5 | F15: =WEEKNUM(A15,2) - WEEKNUM(DATE(YEAR(A15),MONTH(A15),1),2) + 1 -> 3 | G15: 1 | H15: 140 | I15: BANAMEX | J15: REEMBOLSO | M15: =VLOOKUP(J15,RECATALOGANDO!A:C,2,0) -> REEMBOLSO | N15: =VLOOKUP(M15,RECATALOGANDO!B:C,2,0) -> DINERO DEVUELTO A ORIGEN | O15: NO ES INGRESO
A16: 45527 | B16: =DAY(A16) -> 23 | C16: =MONTH(A16) -> 8 | D16: =YEAR(A16) -> 2024 | E16: =WEEKDAY(A16,2) -> 5 | F16: =WEEKNUM(A16,2) - WEEKNUM(DATE(YEAR(A16),MONTH(A16),1),2) + 1 -> 4 | H16: 5000 | I16: BANAMEX | J16: PENSIÓN ALIMENTICIA | M16: =VLOOKUP(J16,RECATALOGANDO!A:C,2,0) -> PENSION ALIMENTICIA | N16: =VLOOKUP(M16,RECATALOGANDO!B:C,2,0) -> PENSION | O16: NO ES INGRESO
A17: 45587 | B17: =DAY(A17) -> 22 | C17: =MONTH(A17) -> 10 | D17: =YEAR(A17) -> 2024 | E17: =WEEKDAY(A17,2) -> 2 | F17: =WEEKNUM(A17,2) - WEEKNUM(DATE(YEAR(A17),MONTH(A17),1),2) + 1 -> 4 | H17: 7800 | I17: BANAMEX | J17: DEPOSITO EQUIVOCADO QUE FUE REEMBOLSADO | M17: =VLOOKUP(J17,RECATALOGANDO!A:C,2,0) -> REEMBOLSO | N17: =VLOOKUP(M17,RECATALOGANDO!B:C,2,0) -> DINERO DEVUELTO A ORIGEN | O17: NO ES INGRESO
A18: 45589 | B18: =DAY(A18) -> 24 | C18: =MONTH(A18) -> 10 | D18: =YEAR(A18) -> 2024 | E18: =WEEKDAY(A18,2) -> 4 | F18: =WEEKNUM(A18,2) - WEEKNUM(DATE(YEAR(A18),MONTH(A18),1),2) + 1 -> 4 | H18: 1340 | I18: BANAMEX | J18: DEVOLUCIÓN SPEI | M18: =VLOOKUP(J18,RECATALOGANDO!A:C,2,0) -> REEMBOLSO | N18: =VLOOKUP(M18,RECATALOGANDO!B:C,2,0) -> DINERO DEVUELTO A ORIGEN | O18: NO ES INGRESO
A19: 45602 | B19: =DAY(A19) -> 6 | C19: =MONTH(A19) -> 11 | D19: =YEAR(A19) -> 2024 | E19: =WEEKDAY(A19,2) -> 3 | F19: =WEEKNUM(A19,2) - WEEKNUM(DATE(YEAR(A19),MONTH(A19),1),2) + 1 -> 2 | H19: 226309.64 | I19: BBVA | J19: DEPOSITO PENSION ALIMENTICIA | M19: =VLOOKUP(J19,RECATALOGANDO!A:C,2,0) -> PENSION ALIMENTICIA | N19: =VLOOKUP(M19,RECATALOGANDO!B:C,2,0) -> PENSION | O19: NO ES INGRESO
A20: 45693 | B20: =DAY(A20) -> 5 | C20: =MONTH(A20) -> 2 | D20: =YEAR(A20) -> 2025 | E20: =WEEKDAY(A20,2) -> 3 | F20: =WEEKNUM(A20,2) - WEEKNUM(DATE(YEAR(A20),MONTH(A20),1),2) + 1 -> 2 | H20: 676.46 | I20: BANAMEX | J20: ABONO POR REEMBOLSO POR CARGO NO RECONOCIDO | M20: =VLOOKUP(J20,RECATALOGANDO!A:C,2,0) -> REEMBOLSO | N20: =VLOOKUP(M20,RECATALOGANDO!B:C,2,0) -> DINERO DEVUELTO A ORIGEN | O20: NO ES INGRESO
A21: 45695 | B21: =DAY(A21) -> 7 | C21: =MONTH(A21) -> 2 | D21: =YEAR(A21) -> 2025 | E21: =WEEKDAY(A21,2) -> 5 | F21: =WEEKNUM(A21,2) - WEEKNUM(DATE(YEAR(A21),MONTH(A21),1),2) + 1 -> 2 | H21: 676.46 | I21: BANAMEX | J21: ABONO POR REEMBOLSO POR CARGO NO RECONOCIDO | M21: =VLOOKUP(J21,RECATALOGANDO!A:C,2,0) -> REEMBOLSO | N21: =VLOOKUP(M21,RECATALOGANDO!B:C,2,0) -> DINERO DEVUELTO A ORIGEN | O21: NO ES INGRESO
A22: 45698 | B22: =DAY(A22) -> 10 | C22: =MONTH(A22) -> 2 | D22: =YEAR(A22) -> 2025 | E22: =WEEKDAY(A22,2) -> 1 | F22: =WEEKNUM(A22,2) - WEEKNUM(DATE(YEAR(A22),MONTH(A22),1),2) + 1 -> 3 | H22: 676.46 | I22: BANAMEX | J22: ABONO POR REEMBOLSO POR CARGO NO RECONOCIDO | M22: =VLOOKUP(J22,RECATALOGANDO!A:C,2,0) -> REEMBOLSO | N22: =VLOOKUP(M22,RECATALOGANDO!B:C,2,0) -> DINERO DEVUELTO A ORIGEN | O22: NO ES INGRESO
A23: 44930 | B23: =DAY(A23) -> 4 | C23: =MONTH(A23) -> 1 | D23: =YEAR(A23) -> 2023 | E23: =WEEKDAY(A23,2) -> 3 | F23: =WEEKNUM(A23,2) - WEEKNUM(DATE(YEAR(A23),MONTH(A23),1),2) + 1 -> 2 | H23: 1000 | I23: BANAMEX | J23: TRANFERENCIA ENTRE CUENTAS | M23: =VLOOKUP(J23,RECATALOGANDO!A:C,2,0) -> TRANSFERENCIA ENTRE CUENTAS | N23: =VLOOKUP(M23,RECATALOGANDO!B:C,2,0) -> TRANSFERENCIAS | O23: TRANSFERENCIAS
A24: 44941 | B24: =DAY(A24) -> 15 | C24: =MONTH(A24) -> 1 | D24: =YEAR(A24) -> 2023 | E24: =WEEKDAY(A24,2) -> 7 | F24: =WEEKNUM(A24,2) - WEEKNUM(DATE(YEAR(A24),MONTH(A24),1),2) + 1 -> 3 | H24: 200 | I24: BBVA | J24: TRANFERENCIA ENTRE CUENTAS | M24: =VLOOKUP(J24,RECATALOGANDO!A:C,2,0) -> TRANSFERENCIA ENTRE CUENTAS | N24: =VLOOKUP(M24,RECATALOGANDO!B:C,2,0) -> TRANSFERENCIAS | O24: TRANSFERENCIAS
A25: 44956 | B25: =DAY(A25) -> 30 | C25: =MONTH(A25) -> 1 | D25: =YEAR(A25) -> 2023 | E25: =WEEKDAY(A25,2) -> 1 | F25: =WEEKNUM(A25,2) - WEEKNUM(DATE(YEAR(A25),MONTH(A25),1),2) + 1 -> 6 | G25: 2 | H25: 700 | I25: BBVA | J25: TRANSFERENCIA ENTRE CUENTAS | M25: =VLOOKUP(J25,RECATALOGANDO!A:C,2,0) -> TRANSFERENCIA ENTRE CUENTAS | N25: =VLOOKUP(M25,RECATALOGANDO!B:C,2,0) -> TRANSFERENCIAS | O25: TRANSFERENCIAS
A26: 44956 | B26: =DAY(A26) -> 30 | C26: =MONTH(A26) -> 1 | D26: =YEAR(A26) -> 2023 | E26: =WEEKDAY(A26,2) -> 1 | F26: =WEEKNUM(A26,2) - WEEKNUM(DATE(YEAR(A26),MONTH(A26),1),2) + 1 -> 6 | G26: 2 | H26: 700 | I26: BBVA | J26: TRANSFERENCIA ENTRE CUENTAS | M26: =VLOOKUP(J26,RECATALOGANDO!A:C,2,0) -> TRANSFERENCIA ENTRE CUENTAS | N26: =VLOOKUP(M26,RECATALOGANDO!B:C,2,0) -> TRANSFERENCIAS | O26: TRANSFERENCIAS
A27: 44958 | B27: =DAY(A27) -> 1 | C27: =MONTH(A27) -> 2 | D27: =YEAR(A27) -> 2023 | E27: =WEEKDAY(A27,2) -> 3 | F27: =WEEKNUM(A27,2) - WEEKNUM(DATE(YEAR(A27),MONTH(A27),1),2) + 1 -> 1 | H27: 1000 | I27: BANAMEX | J27: TRANSFERENCIA ENTRE CUENTAS | M27: =VLOOKUP(J27,RECATALOGANDO!A:C,2,0) -> TRANSFERENCIA ENTRE CUENTAS | N27: =VLOOKUP(M27,RECATALOGANDO!B:C,2,0) -> TRANSFERENCIAS | O27: TRANSFERENCIAS
A28: 44958 | B28: =DAY(A28) -> 1 | C28: =MONTH(A28) -> 2 | D28: =YEAR(A28) -> 2023 | E28: =WEEKDAY(A28,2) -> 3 | F28: =WEEKNUM(A28,2) - WEEKNUM(DATE(YEAR(A28),MONTH(A28),1),2) + 1 -> 1 | H28: 1000 | I28: BANAMEX | J28: TRANSFERENCIA ENTRE CUENTAS | M28: =VLOOKUP(J28,RECATALOGANDO!A:C,2,0) -> TRANSFERENCIA ENTRE CUENTAS | N28: =VLOOKUP(M28,RECATALOGANDO!B:C,2,0) -> TRANSFERENCIAS | O28: TRANSFERENCIAS
A29: 44965 | B29: =DAY(A29) -> 8 | C29: =MONTH(A29) -> 2 | D29: =YEAR(A29) -> 2023 | E29: =WEEKDAY(A29,2) -> 3 | F29: =WEEKNUM(A29,2) - WEEKNUM(DATE(YEAR(A29),MONTH(A29),1),2) + 1 -> 2 | H29: 500 | I29: BANAMEX | J29: TRANSFERENCIA ENTRE CUENTAS | M29: =VLOOKUP(J29,RECATALOGANDO!A:C,2,0) -> TRANSFERENCIA ENTRE CUENTAS | N29: =VLOOKUP(M29,RECATALOGANDO!B:C,2,0) -> TRANSFERENCIAS | O29: TRANSFERENCIAS
A30: 44965 | B30: =DAY(A30) -> 8 | C30: =MONTH(A30) -> 2 | D30: =YEAR(A30) -> 2023 | E30: =WEEKDAY(A30,2) -> 3 | F30: =WEEKNUM(A30,2) - WEEKNUM(DATE(YEAR(A30),MONTH(A30),1),2) + 1 -> 2 | H30: 500 | I30: BANAMEX | J30: TRANSFERENCIA ENTRE CUENTAS | M30: =VLOOKUP(J30,RECATALOGANDO!A:C,2,0) -> TRANSFERENCIA ENTRE CUENTAS | N30: =VLOOKUP(M30,RECATALOGANDO!B:C,2,0) -> TRANSFERENCIAS | O30: TRANSFERENCIAS
A31: 44970 | B31: =DAY(A31) -> 13 | C31: =MONTH(A31) -> 2 | D31: =YEAR(A31) -> 2023 | E31: =WEEKDAY(A31,2) -> 1 | F31: =WEEKNUM(A31,2) - WEEKNUM(DATE(YEAR(A31),MONTH(A31),1),2) + 1 -> 3 | H31: 1700 | I31: BANAMEX | J31: TRANSFERENCIA ENTRE CUENTAS | M31: =VLOOKUP(J31,RECATALOGANDO!A:C,2,0) -> TRANSFERENCIA ENTRE CUENTAS | N31: =VLOOKUP(M31,RECATALOGANDO!B:C,2,0) -> TRANSFERENCIAS | O31: TRANSFERENCIAS
A32: 44970 | B32: =DAY(A32) -> 13 | C32: =MONTH(A32) -> 2 | D32: =YEAR(A32) -> 2023 | E32: =WEEKDAY(A32,2) -> 1 | F32: =WEEKNUM(A32,2) - WEEKNUM(DATE(YEAR(A32),MONTH(A32),1),2) + 1 -> 3 | H32: 1700 | I32: BANAMEX | J32: TRANSFERENCIA ENTRE CUENTAS | M32: =VLOOKUP(J32,RECATALOGANDO!A:C,2,0) -> TRANSFERENCIA ENTRE CUENTAS | N32: =VLOOKUP(M32,RECATALOGANDO!B:C,2,0) -> TRANSFERENCIAS | O32: TRANSFERENCIAS
A33: 44974 | B33: =DAY(A33) -> 17 | C33: =MONTH(A33) -> 2 | D33: =YEAR(A33) -> 2023 | E33: =WEEKDAY(A33,2) -> 5 | F33: =WEEKNUM(A33,2) - WEEKNUM(DATE(YEAR(A33),MONTH(A33),1),2) + 1 -> 3 | H33: 900 | I33: BBVA | J33: TRANSFERENCIA ENTRE CUENTAS | M33: =VLOOKUP(J33,RECATALOGANDO!A:C,2,0) -> TRANSFERENCIA ENTRE CUENTAS | N33: =VLOOKUP(M33,RECATALOGANDO!B:C,2,0) -> TRANSFERENCIAS | O33: TRANSFERENCIAS
A34: 44974 | B34: =DAY(A34) -> 17 | C34: =MONTH(A34) -> 2 | D34: =YEAR(A34) -> 2023 | E34: =WEEKDAY(A34,2) -> 5 | F34: =WEEKNUM(A34,2) - WEEKNUM(DATE(YEAR(A34),MONTH(A34),1),2) + 1 -> 3 | H34: 900 | I34: BBVA | J34: TRANSFERENCIA ENTRE CUENTAS | M34: =VLOOKUP(J34,RECATALOGANDO!A:C,2,0) -> TRANSFERENCIA ENTRE CUENTAS | N34: =VLOOKUP(M34,RECATALOGANDO!B:C,2,0) -> TRANSFERENCIAS | O34: TRANSFERENCIAS
A35: 44982 | B35: =DAY(A35) -> 25 | C35: =MONTH(A35) -> 2 | D35: =YEAR(A35) -> 2023 | E35: =WEEKDAY(A35,2) -> 6 | F35: =WEEKNUM(A35,2) - WEEKNUM(DATE(YEAR(A35),MONTH(A35),1),2) + 1 -> 4 | H35: 500 | I35: BBVA | J35: TRANSFERENCIA ENTRE CUENTAS | M35: =VLOOKUP(J35,RECATALOGANDO!A:C,2,0) -> TRANSFERENCIA ENTRE CUENTAS | N35: =VLOOKUP(M35,RECATALOGANDO!B:C,2,0) -> TRANSFERENCIAS | O35: TRANSFERENCIAS
A36: 44982 | B36: =DAY(A36) -> 25 | C36: =MONTH(A36) -> 2 | D36: =YEAR(A36) -> 2023 | E36: =WEEKDAY(A36,2) -> 6 | F36: =WEEKNUM(A36,2) - WEEKNUM(DATE(YEAR(A36),MONTH(A36),1),2) + 1 -> 4 | H36: 500 | I36: BBVA | J36: TRANSFERENCIA ENTRE CUENTAS | M36: =VLOOKUP(J36,RECATALOGANDO!A:C,2,0) -> TRANSFERENCIA ENTRE CUENTAS | N36: =VLOOKUP(M36,RECATALOGANDO!B:C,2,0) -> TRANSFERENCIAS | O36: TRANSFERENCIAS
A37: 44988 | B37: =DAY(A37) -> 3 | C37: =MONTH(A37) -> 3 | D37: =YEAR(A37) -> 2023 | E37: =WEEKDAY(A37,2) -> 5 | F37: =WEEKNUM(A37,2) - WEEKNUM(DATE(YEAR(A37),MONTH(A37),1),2) + 1 -> 1 | H37: 800 | I37: BBVA | J37: TRANSFERENCIA ENTRE CUENTAS | M37: =VLOOKUP(J37,RECATALOGANDO!A:C,2,0) -> TRANSFERENCIA ENTRE CUENTAS | N37: =VLOOKUP(M37,RECATALOGANDO!B:C,2,0) -> TRANSFERENCIAS | O37: TRANSFERENCIAS
A38: 44995 | B38: =DAY(A38) -> 10 | C38: =MONTH(A38) -> 3 | D38: =YEAR(A38) -> 2023 | E38: =WEEKDAY(A38,2) -> 5 | F38: =WEEKNUM(A38,2) - WEEKNUM(DATE(YEAR(A38),MONTH(A38),1),2) + 1 -> 2 | H38: 100 | I38: BANAMEX | J38: TRANSFERENCIA ENTRE CUENTAS | M38: =VLOOKUP(J38,RECATALOGANDO!A:C,2,0) -> TRANSFERENCIA ENTRE CUENTAS | N38: =VLOOKUP(M38,RECATALOGANDO!B:C,2,0) -> TRANSFERENCIAS | O38: TRANSFERENCIAS
... A72: 45217 | B72: =DAY(A72) -> 18 | C72: =MONTH(A72) -> 10 | D72: =YEAR(A72) -> 2023 | E72: =WEEKDAY(A72,2) -> 3 | F72: =WEEKNUM(A72,2) - WEEKNUM(DATE(YEAR(A72),MONTH(A72),1),2) + 1 -> 4 | H72: 2100 | I72: BANAMEX | J72: TRANSFERENCIA ENTRE CUENTAS | M72: =VLOOKUP(J72,RECATALOGANDO!A:C,2,0) -> TRANSFERENCIA ENTRE CUENTAS | N72: =VLOOKUP(M72,RECATALOGANDO!B:C,2,0) -> TRANSFERENCIAS | O72: TRANSFERENCIAS
A73: 45229 | B73: =DAY(A73) -> 30 | C73: =MONTH(A73) -> 10 | D73: =YEAR(A73) -> 2023 | E73: =WEEKDAY(A73,2) -> 1 | F73: =WEEKNUM(A73,2) - WEEKNUM(DATE(YEAR(A73),MONTH(A73),1),2) + 1 -> 6 | G73: 2 | H73: 565 | I73: BANAMEX | J73: TRANSFERENCIA ENTRE CUENTAS | M73: =VLOOKUP(J73,RECATALOGANDO!A:C,2,0) -> TRANSFERENCIA ENTRE CUENTAS | N73: =VLOOKUP(M73,RECATALOGANDO!B:C,2,0) -> TRANSFERENCIAS | O73: TRANSFERENCIAS
A74: 45237 | B74: =DAY(A74) -> 7 | C74: =MONTH(A74) -> 11 | D74: =YEAR(A74) -> 2023 | E74: =WEEKDAY(A74,2) -> 2 | F74: =WEEKNUM(A74,2) - WEEKNUM(DATE(YEAR(A74),MONTH(A74),1),2) + 1 -> 2 | H74: 2375 | I74: BBVA | J74: DEPOSITO FAMILIAR | M74: =VLOOKUP(J74,RECATALOGANDO!A:C,2,0) -> TRANSFERENCIA FAMILIAR | N74: =VLOOKUP(M74,RECATALOGANDO!B:C,2,0) -> TRANSFERENCIAS | O74: TRANSFERENCIAS
A75: 45251 | B75: =DAY(A75) -> 21 | C75: =MONTH(A75) -> 11 | D75: =YEAR(A75) -> 2023 | E75: =WEEKDAY(A75,2) -> 2 | F75: =WEEKNUM(A75,2) - WEEKNUM(DATE(YEAR(A75),MONTH(A75),1),2) + 1 -> 4 | H75: 300 | I75: BANAMEX | J75: TRANSFERENCIA ENTRE CUENTAS | M75: =VLOOKUP(J75,RECATALOGANDO!A:C,2,0) -> TRANSFERENCIA ENTRE CUENTAS | N75: =VLOOKUP(M75,RECATALOGANDO!B:C,2,0) -> TRANSFERENCIAS | O75: TRANSFERENCIAS
A76: 45252 | B76: =DAY(A76) -> 22 | C76: =MONTH(A76) -> 11 | D76: =YEAR(A76) -> 2023 | E76: =WEEKDAY(A76,2) -> 3 | F76: =WEEKNUM(A76,2) - WEEKNUM(DATE(YEAR(A76),MONTH(A76),1),2) + 1 -> 4 | H76: 1000 | I76: BANAMEX | J76: TRANSFERENCIA ENTRE CUENTAS | M76: =VLOOKUP(J76,RECATALOGANDO!A:C,2,0) -> TRANSFERENCIA ENTRE CUENTAS | N76: =VLOOKUP(M76,RECATALOGANDO!B:C,2,0) -> TRANSFERENCIAS | O76: TRANSFERENCIAS
A77: 45253 | B77: =DAY(A77) -> 23 | C77: =MONTH(A77) -> 11 | D77: =YEAR(A77) -> 2023 | E77: =WEEKDAY(A77,2) -> 4 | F77: =WEEKNUM(A77,2) - WEEKNUM(DATE(YEAR(A77),MONTH(A77),1),2) + 1 -> 4 | H77: 300 | I77: BANAMEX | J77: TRANSFERENCIA ENTRE CUENTAS | M77: =VLOOKUP(J77,RECATALOGANDO!A:C,2,0) -> TRANSFERENCIA ENTRE CUENTAS | N77: =VLOOKUP(M77,RECATALOGANDO!B:C,2,0) -> TRANSFERENCIAS | O77: TRANSFERENCIAS
A78: 45253 | B78: =DAY(A78) -> 23 | C78: =MONTH(A78) -> 11 | D78: =YEAR(A78) -> 2023 | E78: =WEEKDAY(A78,2) -> 4 | F78: =WEEKNUM(A78,2) - WEEKNUM(DATE(YEAR(A78),MONTH(A78),1),2) + 1 -> 4 | H78: 950 | I78: BANAMEX | J78: TRANSFERENCIA ENTRE CUENTAS | M78: =VLOOKUP(J78,RECATALOGANDO!A:C,2,0) -> TRANSFERENCIA ENTRE CUENTAS | N78: =VLOOKUP(M78,RECATALOGANDO!B:C,2,0) -> TRANSFERENCIAS | O78: TRANSFERENCIAS
A79: 45269 | B79: =DAY(A79) -> 9 | C79: =MONTH(A79) -> 12 | D79: =YEAR(A79) -> 2023 | E79: =WEEKDAY(A79,2) -> 6 | F79: =WEEKNUM(A79,2) - WEEKNUM(DATE(YEAR(A79),MONTH(A79),1),2) + 1 -> 2 | H79: 800 | I79: BBVA | J79: TRANSFERENCIA ENTRE CUENTAS | M79: =VLOOKUP(J79,RECATALOGANDO!A:C,2,0) -> TRANSFERENCIA ENTRE CUENTAS | N79: =VLOOKUP(M79,RECATALOGANDO!B:C,2,0) -> TRANSFERENCIAS | O79: TRANSFERENCIAS
A80: 45269 | B80: =DAY(A80) -> 9 | C80: =MONTH(A80) -> 12 | D80: =YEAR(A80) -> 2023 | E80: =WEEKDAY(A80,2) -> 6 | F80: =WEEKNUM(A80,2) - WEEKNUM(DATE(YEAR(A80),MONTH(A80),1),2) + 1 -> 2 | H80: 3000 | I80: BBVA | J80: TRANSFERENCIA ENTRE CUENTAS | M80: =VLOOKUP(J80,RECATALOGANDO!A:C,2,0) -> TRANSFERENCIA ENTRE CUENTAS | N80: =VLOOKUP(M80,RECATALOGANDO!B:C,2,0) -> TRANSFERENCIAS | O80: TRANSFERENCIAS
A81: 45271 | B81: =DAY(A81) -> 11 | C81: =MONTH(A81) -> 12 | D81: =YEAR(A81) -> 2023 | E81: =WEEKDAY(A81,2) -> 1 | F81: =WEEKNUM(A81,2) - WEEKNUM(DATE(YEAR(A81),MONTH(A81),1),2) + 1 -> 3 | H81: 1000 | I81: BBVA | J81: DEPOSITO FAMILIAR | M81: =VLOOKUP(J81,RECATALOGANDO!A:C,2,0) -> TRANSFERENCIA FAMILIAR | N81: =VLOOKUP(M81,RECATALOGANDO!B:C,2,0) -> TRANSFERENCIAS | O81: TRANSFERENCIAS
A82: 45274 | B82: =DAY(A82) -> 14 | C82: =MONTH(A82) -> 12 | D82: =YEAR(A82) -> 2023 | E82: =WEEKDAY(A82,2) -> 4 | F82: =WEEKNUM(A82,2) - WEEKNUM(DATE(YEAR(A82),MONTH(A82),1),2) + 1 -> 3 | H82: 500 | I82: BBVA | J82: DEPOSITO FAMILIAR | M82: =VLOOKUP(J82,RECATALOGANDO!A:C,2,0) -> TRANSFERENCIA FAMILIAR | N82: =VLOOKUP(M82,RECATALOGANDO!B:C,2,0) -> TRANSFERENCIAS | O82: TRANSFERENCIAS
A83: 45275 | B83: =DAY(A83) -> 15 | C83: =MONTH(A83) -> 12 | D83: =YEAR(A83) -> 2023 | E83: =WEEKDAY(A83,2) -> 5 | F83: =WEEKNUM(A83,2) - WEEKNUM(DATE(YEAR(A83),MONTH(A83),1),2) + 1 -> 3 | G83: 1 | H83: 800 | I83: BBVA | J83: TRANSFERENCIA ENTRE CUENTAS | M83: =VLOOKUP(J83,RECATALOGANDO!A:C,2,0) -> TRANSFERENCIA ENTRE CUENTAS | N83: =VLOOKUP(M83,RECATALOGANDO!B:C,2,0) -> TRANSFERENCIAS | O83: TRANSFERENCIAS
A84: 45275 | B84: =DAY(A84) -> 15 | C84: =MONTH(A84) -> 12 | D84: =YEAR(A84) -> 2023 | E84: =WEEKDAY(A84,2) -> 5 | F84: =WEEKNUM(A84,2) - WEEKNUM(DATE(YEAR(A84),MONTH(A84),1),2) + 1 -> 3 | G84: 1 | H84: 1600 | I84: BBVA | J84: DEPOSITO FAMILIAR | M84: =VLOOKUP(J84,RECATALOGANDO!A:C,2,0) -> TRANSFERENCIA FAMILIAR | N84: =VLOOKUP(M84,RECATALOGANDO!B:C,2,0) -> TRANSFERENCIAS | O84: TRANSFERENCIAS
A85: 45276 | B85: =DAY(A85) -> 16 | C85: =MONTH(A85) -> 12 | D85: =YEAR(A85) -> 2023 | E85: =WEEKDAY(A85,2) -> 6 | F85: =WEEKNUM(A85,2) - WEEKNUM(DATE(YEAR(A85),MONTH(A85),1),2) + 1 -> 3 | H85: 650 | I85: BBVA | J85: DEPOSITO FAMILIAR | M85: =VLOOKUP(J85,RECATALOGANDO!A:C,2,0) -> TRANSFERENCIA FAMILIAR | N85: =VLOOKUP(M85,RECATALOGANDO!B:C,2,0) -> TRANSFERENCIAS | O85: TRANSFERENCIAS
A86: 45287 | B86: =DAY(A86) -> 27 | C86: =MONTH(A86) -> 12 | D86: =YEAR(A86) -> 2023 | E86: =WEEKDAY(A86,2) -> 3 | F86: =WEEKNUM(A86,2) - WEEKNUM(DATE(YEAR(A86),MONTH(A86),1),2) + 1 -> 5 | H86: 500 | I86: BBVA | J86: TRANSFERENCIA ENTRE CUENTAS | M86: =VLOOKUP(J86,RECATALOGANDO!A:C,2,0) -> TRANSFERENCIA ENTRE CUENTAS | N86: =VLOOKUP(M86,RECATALOGANDO!B:C,2,0) -> TRANSFERENCIAS | O86: TRANSFERENCIAS
A87: 45324 | B87: =DAY(A87) -> 2 | C87: =MONTH(A87) -> 2 | D87: =YEAR(A87) -> 2024 | E87: =WEEKDAY(A87,2) -> 5 | F87: =WEEKNUM(A87,2) - WEEKNUM(DATE(YEAR(A87),MONTH(A87),1),2) + 1 -> 1 | H87: 350 | I87: BBVA | J87: ENTRE CUENTAS | M87: =VLOOKUP(J87,RECATALOGANDO!A:C,2,0) -> TRANSFERENCIA ENTRE CUENTAS | N87: =VLOOKUP(M87,RECATALOGANDO!B:C,2,0) -> TRANSFERENCIAS | O87: TRANSFERENCIAS
A88: 45330 | B88: =DAY(A88) -> 8 | C88: =MONTH(A88) -> 2 | D88: =YEAR(A88) -> 2024 | E88: =WEEKDAY(A88,2) -> 4 | F88: =WEEKNUM(A88,2) - WEEKNUM(DATE(YEAR(A88),MONTH(A88),1),2) + 1 -> 2 | H88: 960 | I88: BBVA | J88: TRANSFERENCIA FAMILIAR | M88: =VLOOKUP(J88,RECATALOGANDO!A:C,2,0) -> TRANSFERENCIA FAMILIAR | N88: =VLOOKUP(M88,RECATALOGANDO!B:C,2,0) -> TRANSFERENCIAS | O88: TRANSFERENCIAS
A89: 45336 | B89: =DAY(A89) -> 14 | C89: =MONTH(A89) -> 2 | D89: =YEAR(A89) -> 2024 | E89: =WEEKDAY(A89,2) -> 3 | F89: =WEEKNUM(A89,2) - WEEKNUM(DATE(YEAR(A89),MONTH(A89),1),2) + 1 -> 3 | H89: 1000 | I89: BANAMEX | J89: ENTRE CUENTAS | M89: =VLOOKUP(J89,RECATALOGANDO!A:C,2,0) -> TRANSFERENCIA ENTRE CUENTAS | N89: =VLOOKUP(M89,RECATALOGANDO!B:C,2,0) -> TRANSFERENCIAS | O89: TRANSFERENCIAS
A90: 45337 | B90: =DAY(A90) -> 15 | C90: =MONTH(A90) -> 2 | D90: =YEAR(A90) -> 2024 | E90: =WEEKDAY(A90,2) -> 4 | F90: =WEEKNUM(A90,2) - WEEKNUM(DATE(YEAR(A90),MONTH(A90),1),2) + 1 -> 3 | G90: 1 | H90: 800 | I90: BBVA | J90: TRANSFERENCIA FAMILIAR | M90: =VLOOKUP(J90,RECATALOGANDO!A:C,2,0) -> TRANSFERENCIA FAMILIAR | N90: =VLOOKUP(M90,RECATALOGANDO!B:C,2,0) -> TRANSFERENCIAS | O90: TRANSFERENCIAS
A91: 45338 | B91: =DAY(A91) -> 16 | C91: =MONTH(A91) -> 2 | D91: =YEAR(A91) -> 2024 | E91: =WEEKDAY(A91,2) -> 5 | F91: =WEEKNUM(A91,2) - WEEKNUM(DATE(YEAR(A91),MONTH(A91),1),2) + 1 -> 3 | H91: 324 | I91: BANAMEX | J91: ENTRE CUENTAS | M91: =VLOOKUP(J91,RECATALOGANDO!A:C,2,0) -> TRANSFERENCIA ENTRE CUENTAS | N91: =VLOOKUP(M91,RECATALOGANDO!B:C,2,0) -> TRANSFERENCIAS | O91: TRANSFERENCIAS
A92: 45338 | B92: =DAY(A92) -> 16 | C92: =MONTH(A92) -> 2 | D92: =YEAR(A92) -> 2024 | E92: =WEEKDAY(A92,2) -> 5 | F92: =WEEKNUM(A92,2) - WEEKNUM(DATE(YEAR(A92),MONTH(A92),1),2) + 1 -> 3 | H92: 2000 | I92: BANAMEX | J92: TRANSFERENCIA FAMILIAR | M92: =VLOOKUP(J92,RECATALOGANDO!A:C,2,0) -> TRANSFERENCIA FAMILIAR | N92: =VLOOKUP(M92,RECATALOGANDO!B:C,2,0) -> TRANSFERENCIAS | O92: TRANSFERENCIAS
A93: 45338 | B93: =DAY(A93) -> 16 | C93: =MONTH(A93) -> 2 | D93: =YEAR(A93) -> 2024 | E93: =WEEKDAY(A93,2) -> 5 | F93: =WEEKNUM(A93,2) - WEEKNUM(DATE(YEAR(A93),MONTH(A93),1),2) + 1 -> 3 | H93: 2900 | I93: BBVA | J93: ENTRE CUENTAS | M93: =VLOOKUP(J93,RECATALOGANDO!A:C,2,0) -> TRANSFERENCIA ENTRE CUENTAS | N93: =VLOOKUP(M93,RECATALOGANDO!B:C,2,0) -> TRANSFERENCIAS | O93: TRANSFERENCIAS
A94: 45342 | B94: =DAY(A94) -> 20 | C94: =MONTH(A94) -> 2 | D94: =YEAR(A94) -> 2024 | E94: =WEEKDAY(A94,2) -> 2 | F94: =WEEKNUM(A94,2) - WEEKNUM(DATE(YEAR(A94),MONTH(A94),1),2) + 1 -> 4 | H94: 1100 | I94: BANAMEX | J94: ENTRE CUENTAS | M94: =VLOOKUP(J94,RECATALOGANDO!A:C,2,0) -> TRANSFERENCIA ENTRE CUENTAS | N94: =VLOOKUP(M94,RECATALOGANDO!B:C,2,0) -> TRANSFERENCIAS | O94: TRANSFERENCIAS
A95: 45352 | B95: =DAY(A95) -> 1 | C95: =MONTH(A95) -> 3 | D95: =YEAR(A95) -> 2024 | E95: =WEEKDAY(A95,2) -> 5 | F95: =WEEKNUM(A95,2) - WEEKNUM(DATE(YEAR(A95),MONTH(A95),1),2) + 1 -> 1 | H95: 300 | I95: BANAMEX | J95: ENTRE CUENTAS | M95: =VLOOKUP(J95,RECATALOGANDO!A:C,2,0) -> TRANSFERENCIA ENTRE CUENTAS | N95: =VLOOKUP(M95,RECATALOGANDO!B:C,2,0) -> TRANSFERENCIAS | O95: TRANSFERENCIAS
A96: 45355 | B96: =DAY(A96) -> 4 | C96: =MONTH(A96) -> 3 | D96: =YEAR(A96) -> 2024 | E96: =WEEKDAY(A96,2) -> 1 | F96: =WEEKNUM(A96,2) - WEEKNUM(DATE(YEAR(A96),MONTH(A96),1),2) + 1 -> 2 | H96: 700 | I96: BBVA | J96: DEPOSITO FAMILIAR | M96: =VLOOKUP(J96,RECATALOGANDO!A:C,2,0) -> TRANSFERENCIA FAMILIAR | N96: =VLOOKUP(M96,RECATALOGANDO!B:C,2,0) -> TRANSFERENCIAS | O96: TRANSFERENCIAS
A97: 45355 | B97: =DAY(A97) -> 4 | C97: =MONTH(A97) -> 3 | D97: =YEAR(A97) -> 2024 | E97: =WEEKDAY(A97,2) -> 1 | F97: =WEEKNUM(A97,2) - WEEKNUM(DATE(YEAR(A97),MONTH(A97),1),2) + 1 -> 2 | H97: 2400 | I97: BANAMEX | J97: DEPOSITO FAMILIAR | M97: =VLOOKUP(J97,RECATALOGANDO!A:C,2,0) -> TRANSFERENCIA FAMILIAR | N97: =VLOOKUP(M97,RECATALOGANDO!B:C,2,0) -> TRANSFERENCIAS | O97: TRANSFERENCIAS
A98: 45357 | B98: =DAY(A98) -> 6 | C98: =MONTH(A98) -> 3 | D98: =YEAR(A98) -> 2024 | E98: =WEEKDAY(A98,2) -> 3 | F98: =WEEKNUM(A98,2) - WEEKNUM(DATE(YEAR(A98),MONTH(A98),1),2) + 1 -> 2 | H98: 450 | I98: BBVA | J98: ENTRE CUENTAS | M98: =VLOOKUP(J98,RECATALOGANDO!A:C,2,0) -> TRANSFERENCIA ENTRE CUENTAS | N98: =VLOOKUP(M98,RECATALOGANDO!B:C,2,0) -> TRANSFERENCIAS | O98: TRANSFERENCIAS
A99: 45357 | B99: =DAY(A99) -> 6 | C99: =MONTH(A99) -> 3 | D99: =YEAR(A99) -> 2024 | E99: =WEEKDAY(A99,2) -> 3 | F99: =WEEKNUM(A99,2) - WEEKNUM(DATE(YEAR(A99),MONTH(A99),1),2) + 1 -> 2 | H99: 2750 | I99: BBVA | J99: DEPOSITO FAMILIAR | M99: =VLOOKUP(J99,RECATALOGANDO!A:C,2,0) -> TRANSFERENCIA FAMILIAR | N99: =VLOOKUP(M99,RECATALOGANDO!B:C,2,0) -> TRANSFERENCIAS | O99: TRANSFERENCIAS
A100: 45365 | B100: =DAY(A100) -> 14 | C100: =MONTH(A100) -> 3 | D100: =YEAR(A100) -> 2024 | E100: =WEEKDAY(A100,2) -> 4 | F100: =WEEKNUM(A100,2) - WEEKNUM(DATE(YEAR(A100),MONTH(A100),1),2) + 1 -> 3 | H100: 2200 | I100: BBVA | J100: DEPOSITO FAMILIAR | M100: =VLOOKUP(J100,RECATALOGANDO!A:C,2,0) -> TRANSFERENCIA FAMILIAR | N100: =VLOOKUP(M100,RECATALOGANDO!B:C,2,0) -> TRANSFERENCIAS | O100: TRANSFERENCIAS
A101: 45369 | B101: =DAY(A101) -> 18 | C101: =MONTH(A101) -> 3 | D101: =YEAR(A101) -> 2024 | E101: =WEEKDAY(A101,2) -> 1 | F101: =WEEKNUM(A101,2) - WEEKNUM(DATE(YEAR(A101),MONTH(A101),1),2) + 1 -> 4 | H101: 500 | I101: BBVA | J101: DEPOSITO FAMILIAR | M101: =VLOOKUP(J101,RECATALOGANDO!A:C,2,0) -> TRANSFERENCIA FAMILIAR | N101: =VLOOKUP(M101,RECATALOGANDO!B:C,2,0) -> TRANSFERENCIAS | O101: TRANSFERENCIAS
A102: 45376 | B102: =DAY(A102) -> 25 | C102: =MONTH(A102) -> 3 | D102: =YEAR(A102) -> 2024 | E102: =WEEKDAY(A102,2) -> 1 | F102: =WEEKNUM(A102,2) - WEEKNUM(DATE(YEAR(A102),MONTH(A102),1),2) + 1 -> 5 | H102: 200 | I102: BANAMEX | J102: ENTRE CUENTAS | M102: =VLOOKUP(J102,RECATALOGANDO!A:C,2,0) -> TRANSFERENCIA ENTRE CUENTAS | N102: =VLOOKUP(M102,RECATALOGANDO!B:C,2,0) -> TRANSFERENCIAS | O102: TRANSFERENCIAS
... A116: 45426 | B116: =DAY(A116) -> 14 | C116: =MONTH(A116) -> 5 | D116: =YEAR(A116) -> 2024 | E116: =WEEKDAY(A116,2) -> 2 | F116: =WEEKNUM(A116,2) - WEEKNUM(DATE(YEAR(A116),MONTH(A116),1),2) + 1 -> 3 | H116: 1500 | I116: BANAMEX | J116: ENTRE CUENTAS | M116: =VLOOKUP(J116,RECATALOGANDO!A:C,2,0) -> TRANSFERENCIA ENTRE CUENTAS | N116: =VLOOKUP(M116,RECATALOGANDO!B:C,2,0) -> TRANSFERENCIAS | O116: TRANSFERENCIAS
A117: 45427 | B117: =DAY(A117) -> 15 | C117: =MONTH(A117) -> 5 | D117: =YEAR(A117) -> 2024 | E117: =WEEKDAY(A117,2) -> 3 | F117: =WEEKNUM(A117,2) - WEEKNUM(DATE(YEAR(A117),MONTH(A117),1),2) + 1 -> 3 | G117: 1 | H117: 500 | I117: BANAMEX | J117: TRANSFERENCIA FAMILIAR | M117: =VLOOKUP(J117,RECATALOGANDO!A:C,2,0) -> TRANSFERENCIA FAMILIAR | N117: =VLOOKUP(M117,RECATALOGANDO!B:C,2,0) -> TRANSFERENCIAS | O117: TRANSFERENCIAS
A118: 45428 | B118: =DAY(A118) -> 16 | C118: =MONTH(A118) -> 5 | D118: =YEAR(A118) -> 2024 | E118: =WEEKDAY(A118,2) -> 4 | F118: =WEEKNUM(A118,2) - WEEKNUM(DATE(YEAR(A118),MONTH(A118),1),2) + 1 -> 3 | H118: 490 | I118: BBVA | J118: TRANSFERENCIA ENTRE CUENTAS | M118: =VLOOKUP(J118,RECATALOGANDO!A:C,2,0) -> TRANSFERENCIA ENTRE CUENTAS | N118: =VLOOKUP(M118,RECATALOGANDO!B:C,2,0) -> TRANSFERENCIAS | O118: TRANSFERENCIAS
A119: 45428 | B119: =DAY(A119) -> 16 | C119: =MONTH(A119) -> 5 | D119: =YEAR(A119) -> 2024 | E119: =WEEKDAY(A119,2) -> 4 | F119: =WEEKNUM(A119,2) - WEEKNUM(DATE(YEAR(A119),MONTH(A119),1),2) + 1 -> 3 | H119: 550 | I119: BANAMEX | J119: TRANSFERENCIA FAMILIAR | M119: =VLOOKUP(J119,RECATALOGANDO!A:C,2,0) -> TRANSFERENCIA FAMILIAR | N119: =VLOOKUP(M119,RECATALOGANDO!B:C,2,0) -> TRANSFERENCIAS | O119: TRANSFERENCIAS
A120: 45428 | B120: =DAY(A120) -> 16 | C120: =MONTH(A120) -> 5 | D120: =YEAR(A120) -> 2024 | E120: =WEEKDAY(A120,2) -> 4 | F120: =WEEKNUM(A120,2) - WEEKNUM(DATE(YEAR(A120),MONTH(A120),1),2) + 1 -> 3 | H120: 800 | I120: BANAMEX | J120: TRANSFERENCIA ENTRE CUENTAS | M120: =VLOOKUP(J120,RECATALOGANDO!A:C,2,0) -> TRANSFERENCIA ENTRE CUENTAS | N120: =VLOOKUP(M120,RECATALOGANDO!B:C,2,0) -> TRANSFERENCIAS | O120: TRANSFERENCIAS
A121: 45432 | B121: =DAY(A121) -> 20 | C121: =MONTH(A121) -> 5 | D121: =YEAR(A121) -> 2024 | E121: =WEEKDAY(A121,2) -> 1 | F121: =WEEKNUM(A121,2) - WEEKNUM(DATE(YEAR(A121),MONTH(A121),1),2) + 1 -> 4 | H121: 200 | I121: BANAMEX | J121: TRANSFERENCIA FAMILIAR | M121: =VLOOKUP(J121,RECATALOGANDO!A:C,2,0) -> TRANSFERENCIA FAMILIAR | N121: =VLOOKUP(M121,RECATALOGANDO!B:C,2,0) -> TRANSFERENCIAS | O121: TRANSFERENCIAS
A122: 45433 | B122: =DAY(A122) -> 21 | C122: =MONTH(A122) -> 5 | D122: =YEAR(A122) -> 2024 | E122: =WEEKDAY(A122,2) -> 2 | F122: =WEEKNUM(A122,2) - WEEKNUM(DATE(YEAR(A122),MONTH(A122),1),2) + 1 -> 4 | H122: 500 | I122: BBVA | J122: TRANSFERENCIA FAMILIAR | M122: =VLOOKUP(J122,RECATALOGANDO!A:C,2,0) -> TRANSFERENCIA FAMILIAR | N122: =VLOOKUP(M122,RECATALOGANDO!B:C,2,0) -> TRANSFERENCIAS | O122: TRANSFERENCIAS
A123: 45433 | B123: =DAY(A123) -> 21 | C123: =MONTH(A123) -> 5 | D123: =YEAR(A123) -> 2024 | E123: =WEEKDAY(A123,2) -> 2 | F123: =WEEKNUM(A123,2) - WEEKNUM(DATE(YEAR(A123),MONTH(A123),1),2) + 1 -> 4 | H123: 1500 | I123: BBVA | J123: TRANSFERENCIA ENTRE CUENTAS | M123: =VLOOKUP(J123,RECATALOGANDO!A:C,2,0) -> TRANSFERENCIA ENTRE CUENTAS | N123: =VLOOKUP(M123,RECATALOGANDO!B:C,2,0) -> TRANSFERENCIAS | O123: TRANSFERENCIAS
A124: 45434 | B124: =DAY(A124) -> 22 | C124: =MONTH(A124) -> 5 | D124: =YEAR(A124) -> 2024 | E124: =WEEKDAY(A124,2) -> 3 | F124: =WEEKNUM(A124,2) - WEEKNUM(DATE(YEAR(A124),MONTH(A124),1),2) + 1 -> 4 | H124: 500 | I124: BANAMEX | J124: TRANSFERENCIA FAMILIAR | M124: =VLOOKUP(J124,RECATALOGANDO!A:C,2,0) -> TRANSFERENCIA FAMILIAR | N124: =VLOOKUP(M124,RECATALOGANDO!B:C,2,0) -> TRANSFERENCIAS | O124: TRANSFERENCIAS
A125: 45434 | B125: =DAY(A125) -> 22 | C125: =MONTH(A125) -> 5 | D125: =YEAR(A125) -> 2024 | E125: =WEEKDAY(A125,2) -> 3 | F125: =WEEKNUM(A125,2) - WEEKNUM(DATE(YEAR(A125),MONTH(A125),1),2) + 1 -> 4 | H125: 614 | I125: BBVA | J125: TRANSFERENCIA FAMILIAR | M125: =VLOOKUP(J125,RECATALOGANDO!A:C,2,0) -> TRANSFERENCIA FAMILIAR | N125: =VLOOKUP(M125,RECATALOGANDO!B:C,2,0) -> TRANSFERENCIAS | O125: TRANSFERENCIAS
A126: 45436 | B126: =DAY(A126) -> 24 | C126: =MONTH(A126) -> 5 | D126: =YEAR(A126) -> 2024 | E126: =WEEKDAY(A126,2) -> 5 | F126: =WEEKNUM(A126,2) - WEEKNUM(DATE(YEAR(A126),MONTH(A126),1),2) + 1 -> 4 | H126: 250 | I126: BANAMEX | J126: TRANSFERENCIA ENTRE CUENTAS | M126: =VLOOKUP(J126,RECATALOGANDO!A:C,2,0) -> TRANSFERENCIA ENTRE CUENTAS | N126: =VLOOKUP(M126,RECATALOGANDO!B:C,2,0) -> TRANSFERENCIAS | O126: TRANSFERENCIAS
A127: 45439 | B127: =DAY(A127) -> 27 | C127: =MONTH(A127) -> 5 | D127: =YEAR(A127) -> 2024 | E127: =WEEKDAY(A127,2) -> 1 | F127: =WEEKNUM(A127,2) - WEEKNUM(DATE(YEAR(A127),MONTH(A127),1),2) + 1 -> 5 | H127: 800 | I127: BANAMEX | J127: TRANSFERENCIA ENTRE CUENTAS | M127: =VLOOKUP(J127,RECATALOGANDO!A:C,2,0) -> TRANSFERENCIA ENTRE CUENTAS | N127: =VLOOKUP(M127,RECATALOGANDO!B:C,2,0) -> TRANSFERENCIAS | O127: TRANSFERENCIAS
A128: 45440 | B128: =DAY(A128) -> 28 | C128: =MONTH(A128) -> 5 | D128: =YEAR(A128) -> 2024 | E128: =WEEKDAY(A128,2) -> 2 | F128: =WEEKNUM(A128,2) - WEEKNUM(DATE(YEAR(A128),MONTH(A128),1),2) + 1 -> 5 | H128: 500 | I128: BANAMEX | J128: TRANSFERENCIA FAMILIAR | M128: =VLOOKUP(J128,RECATALOGANDO!A:C,2,0) -> TRANSFERENCIA FAMILIAR | N128: =VLOOKUP(M128,RECATALOGANDO!B:C,2,0) -> TRANSFERENCIAS | O128: TRANSFERENCIAS
A129: 45440 | B129: =DAY(A129) -> 28 | C129: =MONTH(A129) -> 5 | D129: =YEAR(A129) -> 2024 | E129: =WEEKDAY(A129,2) -> 2 | F129: =WEEKNUM(A129,2) - WEEKNUM(DATE(YEAR(A129),MONTH(A129),1),2) + 1 -> 5 | H129: 800 | I129: BANAMEX | J129: TRANSFERENCIA ENTRE CUENTAS | M129: =VLOOKUP(J129,RECATALOGANDO!A:C,2,0) -> TRANSFERENCIA ENTRE CUENTAS | N129: =VLOOKUP(M129,RECATALOGANDO!B:C,2,0) -> TRANSFERENCIAS | O129: TRANSFERENCIAS
... A138: 45455 | B138: =DAY(A138) -> 12 | C138: =MONTH(A138) -> 6 | D138: =YEAR(A138) -> 2024 | E138: =WEEKDAY(A138,2) -> 3 | F138: =WEEKNUM(A138,2) - WEEKNUM(DATE(YEAR(A138),MONTH(A138),1),2) + 1 -> 3 | H138: 540 | I138: BANAMEX | J138: TRANSFERENCIA FAMILIAR | M138: =VLOOKUP(J138,RECATALOGANDO!A:C,2,0) -> TRANSFERENCIA FAMILIAR | N138: =VLOOKUP(M138,RECATALOGANDO!B:C,2,0) -> TRANSFERENCIAS | O138: TRANSFERENCIAS
A139: 45457 | B139: =DAY(A139) -> 14 | C139: =MONTH(A139) -> 6 | D139: =YEAR(A139) -> 2024 | E139: =WEEKDAY(A139,2) -> 5 | F139: =WEEKNUM(A139,2) - WEEKNUM(DATE(YEAR(A139),MONTH(A139),1),2) + 1 -> 3 | G139: 1 | H139: 400 | I139: BBVA | J139: TRANSFERENCIA FAMILIAR | M139: =VLOOKUP(J139,RECATALOGANDO!A:C,2,0) -> TRANSFERENCIA FAMILIAR | N139: =VLOOKUP(M139,RECATALOGANDO!B:C,2,0) -> TRANSFERENCIAS | O139: TRANSFERENCIAS
A140: 45457 | B140: =DAY(A140) -> 14 | C140: =MONTH(A140) -> 6 | D140: =YEAR(A140) -> 2024 | E140: =WEEKDAY(A140,2) -> 5 | F140: =WEEKNUM(A140,2) - WEEKNUM(DATE(YEAR(A140),MONTH(A140),1),2) + 1 -> 3 | G140: 1 | H140: 583 | I140: BBVA | J140: TRANSFERENCIA ENTRE CUENTAS | M140: =VLOOKUP(J140,RECATALOGANDO!A:C,2,0) -> TRANSFERENCIA ENTRE CUENTAS | N140: =VLOOKUP(M140,RECATALOGANDO!B:C,2,0) -> TRANSFERENCIAS | O140: TRANSFERENCIAS
A141: 45461 | B141: =DAY(A141) -> 18 | C141: =MONTH(A141) -> 6 | D141: =YEAR(A141) -> 2024 | E141: =WEEKDAY(A141,2) -> 2 | F141: =WEEKNUM(A141,2) - WEEKNUM(DATE(YEAR(A141),MONTH(A141),1),2) + 1 -> 4 | H141: 2000 | I141: BBVA | J141: TRANSFERENCIA ENTRE CUENTAS | M141: =VLOOKUP(J141,RECATALOGANDO!A:C,2,0) -> TRANSFERENCIA ENTRE CUENTAS | N141: =VLOOKUP(M141,RECATALOGANDO!B:C,2,0) -> TRANSFERENCIAS | O141: TRANSFERENCIAS
A142: 45463 | B142: =DAY(A142) -> 20 | C142: =MONTH(A142) -> 6 | D142: =YEAR(A142) -> 2024 | E142: =WEEKDAY(A142,2) -> 4 | F142: =WEEKNUM(A142,2) - WEEKNUM(DATE(YEAR(A142),MONTH(A142),1),2) + 1 -> 4 | H142: 300 | I142: BANAMEX | J142: TRANSFERENCIA FAMILIAR | M142: =VLOOKUP(J142,RECATALOGANDO!A:C,2,0) -> TRANSFERENCIA FAMILIAR | N142: =VLOOKUP(M142,RECATALOGANDO!B:C,2,0) -> TRANSFERENCIAS | O142: TRANSFERENCIAS
A143: 45477 | B143: =DAY(A143) -> 4 | C143: =MONTH(A143) -> 7 | D143: =YEAR(A143) -> 2024 | E143: =WEEKDAY(A143,2) -> 4 | F143: =WEEKNUM(A143,2) - WEEKNUM(DATE(YEAR(A143),MONTH(A143),1),2) + 1 -> 1 | H143: 1000 | I143: BBVA | J143: TRANSFERENCIA ENTRE CUENTAS | M143: =VLOOKUP(J143,RECATALOGANDO!A:C,2,0) -> TRANSFERENCIA ENTRE CUENTAS | N143: =VLOOKUP(M143,RECATALOGANDO!B:C,2,0) -> TRANSFERENCIAS | O143: TRANSFERENCIAS
A144: 45479 | B144: =DAY(A144) -> 6 | C144: =MONTH(A144) -> 7 | D144: =YEAR(A144) -> 2024 | E144: =WEEKDAY(A144,2) -> 6 | F144: =WEEKNUM(A144,2) - WEEKNUM(DATE(YEAR(A144),MONTH(A144),1),2) + 1 -> 1 | H144: 2500 | I144: BBVA | J144: TRANSFERENCIA ENTRE CUENTAS | M144: =VLOOKUP(J144,RECATALOGANDO!A:C,2,0) -> TRANSFERENCIA ENTRE CUENTAS | N144: =VLOOKUP(M144,RECATALOGANDO!B:C,2,0) -> TRANSFERENCIAS | O144: TRANSFERENCIAS
A145: 45505 | B145: =DAY(A145) -> 1 | C145: =MONTH(A145) -> 8 | D145: =YEAR(A145) -> 2024 | E145: =WEEKDAY(A145,2) -> 4 | F145: =WEEKNUM(A145,2) - WEEKNUM(DATE(YEAR(A145),MONTH(A145),1),2) + 1 -> 1 | H145: 500 | I145: BANAMEX | J145: TRANSFERENCIA FAMILIAR | M145: =VLOOKUP(J145,RECATALOGANDO!A:C,2,0) -> TRANSFERENCIA FAMILIAR | N145: =VLOOKUP(M145,RECATALOGANDO!B:C,2,0) -> TRANSFERENCIAS | O145: TRANSFERENCIAS
A146: 45505 | B146: =DAY(A146) -> 1 | C146: =MONTH(A146) -> 8 | D146: =YEAR(A146) -> 2024 | E146: =WEEKDAY(A146,2) -> 4 | F146: =WEEKNUM(A146,2) - WEEKNUM(DATE(YEAR(A146),MONTH(A146),1),2) + 1 -> 1 | H146: 500 | I146: BANAMEX | J146: TRANSFERENCIA FAMILIAR | M146: =VLOOKUP(J146,RECATALOGANDO!A:C,2,0) -> TRANSFERENCIA FAMILIAR | N146: =VLOOKUP(M146,RECATALOGANDO!B:C,2,0) -> TRANSFERENCIAS | O146: TRANSFERENCIAS
A147: 45505 | B147: =DAY(A147) -> 1 | C147: =MONTH(A147) -> 8 | D147: =YEAR(A147) -> 2024 | E147: =WEEKDAY(A147,2) -> 4 | F147: =WEEKNUM(A147,2) - WEEKNUM(DATE(YEAR(A147),MONTH(A147),1),2) + 1 -> 1 | H147: 900 | I147: BANAMEX | J147: ENTRE CUENTAS | M147: =VLOOKUP(J147,RECATALOGANDO!A:C,2,0) -> TRANSFERENCIA ENTRE CUENTAS | N147: =VLOOKUP(M147,RECATALOGANDO!B:C,2,0) -> TRANSFERENCIAS | O147: TRANSFERENCIAS
A148: 45505 | B148: =DAY(A148) -> 1 | C148: =MONTH(A148) -> 8 | D148: =YEAR(A148) -> 2024 | E148: =WEEKDAY(A148,2) -> 4 | F148: =WEEKNUM(A148,2) - WEEKNUM(DATE(YEAR(A148),MONTH(A148),1),2) + 1 -> 1 | H148: 900 | I148: BANAMEX | J148: ENTRE CUENTAS | M148: =VLOOKUP(J148,RECATALOGANDO!A:C,2,0) -> TRANSFERENCIA ENTRE CUENTAS | N148: =VLOOKUP(M148,RECATALOGANDO!B:C,2,0) -> TRANSFERENCIAS | O148: TRANSFERENCIAS
A149: 45506 | B149: =DAY(A149) -> 2 | C149: =MONTH(A149) -> 8 | D149: =YEAR(A149) -> 2024 | E149: =WEEKDAY(A149,2) -> 5 | F149: =WEEKNUM(A149,2) - WEEKNUM(DATE(YEAR(A149),MONTH(A149),1),2) + 1 -> 1 | H149: 300 | I149: BANAMEX | J149: ENTRE CUENTAS | M149: =VLOOKUP(J149,RECATALOGANDO!A:C,2,0) -> TRANSFERENCIA ENTRE CUENTAS | N149: =VLOOKUP(M149,RECATALOGANDO!B:C,2,0) -> TRANSFERENCIAS | O149: TRANSFERENCIAS
A150: 45506 | B150: =DAY(A150) -> 2 | C150: =MONTH(A150) -> 8 | D150: =YEAR(A150) -> 2024 | E150: =WEEKDAY(A150,2) -> 5 | F150: =WEEKNUM(A150,2) - WEEKNUM(DATE(YEAR(A150),MONTH(A150),1),2) + 1 -> 1 | H150: 300 | I150: BANAMEX | J150: ENTRE CUENTAS | M150: =VLOOKUP(J150,RECATALOGANDO!A:C,2,0) -> TRANSFERENCIA ENTRE CUENTAS | N150: =VLOOKUP(M150,RECATALOGANDO!B:C,2,0) -> TRANSFERENCIAS | O150: TRANSFERENCIAS
A151: 45506 | B151: =DAY(A151) -> 2 | C151: =MONTH(A151) -> 8 | D151: =YEAR(A151) -> 2024 | E151: =WEEKDAY(A151,2) -> 5 | F151: =WEEKNUM(A151,2) - WEEKNUM(DATE(YEAR(A151),MONTH(A151),1),2) + 1 -> 1 | H151: 644 | I151: BBVA | J151: ENTRE CUENTAS | M151: =VLOOKUP(J151,RECATALOGANDO!A:C,2,0) -> TRANSFERENCIA ENTRE CUENTAS | N151: =VLOOKUP(M151,RECATALOGANDO!B:C,2,0) -> TRANSFERENCIAS | O151: TRANSFERENCIAS
A152: 45506 | B152: =DAY(A152) -> 2 | C152: =MONTH(A152) -> 8 | D152: =YEAR(A152) -> 2024 | E152: =WEEKDAY(A152,2) -> 5 | F152: =WEEKNUM(A152,2) - WEEKNUM(DATE(YEAR(A152),MONTH(A152),1),2) + 1 -> 1 | H152: 644 | I152: BBVA | J152: ENTRE CUENTAS | M152: =VLOOKUP(J152,RECATALOGANDO!A:C,2,0) -> TRANSFERENCIA ENTRE CUENTAS | N152: =VLOOKUP(M152,RECATALOGANDO!B:C,2,0) -> TRANSFERENCIAS | O152: TRANSFERENCIAS
... A162: 45589 | B162: =DAY(A162) -> 24 | C162: =MONTH(A162) -> 10 | D162: =YEAR(A162) -> 2024 | E162: =WEEKDAY(A162,2) -> 4 | F162: =WEEKNUM(A162,2) - WEEKNUM(DATE(YEAR(A162),MONTH(A162),1),2) + 1 -> 4 | H162: 700 | I162: BANAMEX | J162: ENTRE CUENTAS | M162: =VLOOKUP(J162,RECATALOGANDO!A:C,2,0) -> TRANSFERENCIA ENTRE CUENTAS | N162: =VLOOKUP(M162,RECATALOGANDO!B:C,2,0) -> TRANSFERENCIAS | O162: TRANSFERENCIAS
A163: 45611 | B163: =DAY(A163) -> 15 | C163: =MONTH(A163) -> 11 | D163: =YEAR(A163) -> 2024 | E163: =WEEKDAY(A163,2) -> 5 | F163: =WEEKNUM(A163,2) - WEEKNUM(DATE(YEAR(A163),MONTH(A163),1),2) + 1 -> 3 | G163: 1 | H163: 2000 | I163: BANAMEX | J163: TRANSFERENCIA ENTRE CUENTAS | M163: =VLOOKUP(J163,RECATALOGANDO!A:C,2,0) -> TRANSFERENCIA ENTRE CUENTAS | N163: =VLOOKUP(M163,RECATALOGANDO!B:C,2,0) -> TRANSFERENCIAS | O163: TRANSFERENCIAS
...

Sheet BASE
A1: FECHA | B1: DIA | C1: MES | D1: ANIO | E1: TIPO_DIA | F1: NUM_SEM | G1: QNA | H1: MONTO | I1: BANCO | J1: CONCEPTO | K1: COMENTARIOS | L1: SALDO ACUM | M1: RECAT | N1: AGRUPACION | O1: INDICE
A2: 45507 | B2: =DAY(A2) -> 3 | C2: =MONTH(A2) -> 8 | D2: =YEAR(A2) -> 2024 | E2: =WEEKDAY(A2,2) -> 6 | F2: =WEEKNUM(A2,2) - WEEKNUM(DATE(YEAR(A2),MONTH(A2),1),2) + 1 -> 1 | H2: 277 | I2: BBVA | M2: NO DATO | N2: NO DATO | O2: NO DATO
A3: 45519 | B3: =DAY(A3) -> 15 | C3: =MONTH(A3) -> 8 | D3: =YEAR(A3) -> 2024 | E3: =WEEKDAY(A3,2) -> 4 | F3: =WEEKNUM(A3,2) - WEEKNUM(DATE(YEAR(A3),MONTH(A3),1),2) + 1 -> 3 | G3: 1 | H3: 729.22 | I3: BBVA | M3: NO DATO | N3: NO DATO | O3: NO DATO
A4: 45522 | B4: =DAY(A4) -> 18 | C4: =MONTH(A4) -> 8 | D4: =YEAR(A4) -> 2024 | E4: =WEEKDAY(A4,2) -> 7 | F4: =WEEKNUM(A4,2) - WEEKNUM(DATE(YEAR(A4),MONTH(A4),1),2) + 1 -> 3 | H4: 1856.11 | I4: BBVA | M4: NO DATO | N4: NO DATO | O4: NO DATO
A5: 45524 | B5: =DAY(A5) -> 20 | C5: =MONTH(A5) -> 8 | D5: =YEAR(A5) -> 2024 | E5: =WEEKDAY(A5,2) -> 2 | F5: =WEEKNUM(A5,2) - WEEKNUM(DATE(YEAR(A5),MONTH(A5),1),2) + 1 -> 4 | H5: 1043.51 | I5: BBVA | M5: NO DATO | N5: NO DATO | O5: NO DATO
A6: 45529 | B6: =DAY(A6) -> 25 | C6: =MONTH(A6) -> 8 | D6: =YEAR(A6) -> 2024 | E6: =WEEKDAY(A6,2) -> 7 | F6: =WEEKNUM(A6,2) - WEEKNUM(DATE(YEAR(A6),MONTH(A6),1),2) + 1 -> 4 | H6: 575.67 | I6: BBVA | M6: NO DATO | N6: NO DATO | O6: NO DATO
A7: 44968 | B7: =DAY(A7) -> 11 | C7: =MONTH(A7) -> 2 | D7: =YEAR(A7) -> 2023 | E7: =WEEKDAY(A7,2) -> 6 | F7: =WEEKNUM(A7,2) - WEEKNUM(DATE(YEAR(A7),MONTH(A7),1),2) + 1 -> 2 | H7: 1815 | I7: BBVA | J7: DONATIVO | M7: =VLOOKUP(J7,RECATALOGANDO!A:C,2,0) -> DONATIVO | N7: =VLOOKUP(M7,RECATALOGANDO!B:C,2,0) -> DONATIVO | O7: NO ES INGRESO
A8: 44968 | B8: =DAY(A8) -> 11 | C8: =MONTH(A8) -> 2 | D8: =YEAR(A8) -> 2023 | E8: =WEEKDAY(A8,2) -> 6 | F8: =WEEKNUM(A8,2) - WEEKNUM(DATE(YEAR(A8),MONTH(A8),1),2) + 1 -> 2 | H8: 1815 | I8: BBVA | J8: DONATIVO | M8: =VLOOKUP(J8,RECATALOGANDO!A:C,2,0) -> DONATIVO | N8: =VLOOKUP(M8,RECATALOGANDO!B:C,2,0) -> DONATIVO | O8: NO ES INGRESO
A9: 45118 | B9: =DAY(A9) -> 11 | C9: =MONTH(A9) -> 7 | D9: =YEAR(A9) -> 2023 | E9: =WEEKDAY(A9,2) -> 2 | F9: =WEEKNUM(A9,2) - WEEKNUM(DATE(YEAR(A9),MONTH(A9),1),2) + 1 -> 3 | H9: 55900 | I9: BBVA | J9: PRESTAMO BANCARIO | M9: =VLOOKUP(J9,RECATALOGANDO!A:C,2,0) -> PRESTAMO BANCARIO | N9: =VLOOKUP(M9,RECATALOGANDO!B:C,2,0) -> PRESTAMO | O9: NO ES INGRESO
A10: 45173 | B10: =DAY(A10) -> 4 | C10: =MONTH(A10) -> 9 | D10: =YEAR(A10) -> 2023 | E10: =WEEKDAY(A10,2) -> 1 | F10: =WEEKNUM(A10,2) - WEEKNUM(DATE(YEAR(A10),MONTH(A10),1),2) + 1 -> 2 | H10: 26571 | I10: BANAMEX | J10: DEPÓSITO EQUIVOCADO Y DEVUELTO | M10: =VLOOKUP(J10,RECATALOGANDO!A:C,2,0) -> REEMBOLSO | N10: =VLOOKUP(M10,RECATALOGANDO!B:C,2,0) -> DINERO DEVUELTO A ORIGEN | O10: NO ES INGRESO
A11: 45181 | B11: =DAY(A11) -> 12 | C11: =MONTH(A11) -> 9 | D11: =YEAR(A11) -> 2023 | E11: =WEEKDAY(A11,2) -> 2 | F11: =WEEKNUM(A11,2) - WEEKNUM(DATE(YEAR(A11),MONTH(A11),1),2) + 1 -> 3 | H11: 80000 | I11: BBVA | J11: DEPÓSITO PRESTAMO | M11: =VLOOKUP(J11,RECATALOGANDO!A:C,2,0) -> DEPÓSITO PRESTAMO | N11: =VLOOKUP(M11,RECATALOGANDO!B:C,2,0) -> PRESTAMO | O11: NO ES INGRESO
A12: 45215 | B12: =DAY(A12) -> 16 | C12: =MONTH(A12) -> 10 | D12: =YEAR(A12) -> 2023 | E12: =WEEKDAY(A12,2) -> 1 | F12: =WEEKNUM(A12,2) - WEEKNUM(DATE(YEAR(A12),MONTH(A12),1),2) + 1 -> 4 | H12: 200 | I12: BANAMEX | J12: REEMBOLSO | M12: =VLOOKUP(J12,RECATALOGANDO!A:C,2,0) -> REEMBOLSO | N12: =VLOOKUP(M12,RECATALOGANDO!B:C,2,0) -> DINERO DEVUELTO A ORIGEN | O12: NO ES INGRESO
A13: 45282 | B13: =DAY(A13) -> 22 | C13: =MONTH(A13) -> 12 | D13: =YEAR(A13) -> 2023 | E13: =WEEKDAY(A13,2) -> 5 | F13: =WEEKNUM(A13,2) - WEEKNUM(DATE(YEAR(A13),MONTH(A13),1),2) + 1 -> 4 | H13: 2895 | I13: BBVA | J13: REEMBOLSO POR DEPOSITO EQUIVOCADO | M13: =VLOOKUP(J13,RECATALOGANDO!A:C,2,0) -> REEMBOLSO | N13: =VLOOKUP(M13,RECATALOGANDO!B:C,2,0) -> DINERO DEVUELTO A ORIGEN | O13: NO ES INGRESO
A14: 45365 | B14: =DAY(A14) -> 14 | C14: =MONTH(A14) -> 3 | D14: =YEAR(A14) -> 2024 | E14: =WEEKDAY(A14,2) -> 4 | F14: =WEEKNUM(A14,2) - WEEKNUM(DATE(YEAR(A14),MONTH(A14),1),2) + 1 -> 3 | H14: 3500 | I14: BBVA | J14: REEMBOLSO | M14: =VLOOKUP(J14,RECATALOGANDO!A:C,2,0) -> REEMBOLSO | N14: =VLOOKUP(M14,RECATALOGANDO!B:C,2,0) -> DINERO DEVUELTO A ORIGEN | O14: NO ES INGRESO
A15: 45366 | B15: =DAY(A15) -> 15 | C15: =MONTH(A15) -> 3 | D15: =YEAR(A15) -> 2024 | E15: =WEEKDAY(A15,2) -> 5 | F15: =WEEKNUM(A15,2) - WEEKNUM(DATE(YEAR(A15),MONTH(A15),1),2) + 1 -> 3 | G15: 1 | H15: 140 | I15: BANAMEX | J15: REEMBOLSO | M15: =VLOOKUP(J15,RECATALOGANDO!A:C,2,0) -> REEMBOLSO | N15: =VLOOKUP(M15,RECATALOGANDO!B:C,2,0) -> DINERO DEVUELTO A ORIGEN | O15: NO ES INGRESO
A16: 45527 | B16: =DAY(A16) -> 23 | C16: =MONTH(A16) -> 8 | D16: =YEAR(A16) -> 2024 | E16: =WEEKDAY(A16,2) -> 5 | F16: =WEEKNUM(A16,2) - WEEKNUM(DATE(YEAR(A16),MONTH(A16),1),2) + 1 -> 4 | H16: 5000 | I16: BANAMEX | J16: PENSIÓN ALIMENTICIA | M16: =VLOOKUP(J16,RECATALOGANDO!A:C,2,0) -> PENSION ALIMENTICIA | N16: =VLOOKUP(M16,RECATALOGANDO!B:C,2,0) -> PENSION | O16: NO ES INGRESO
A17: 45587 | B17: =DAY(A17) -> 22 | C17: =MONTH(A17) -> 10 | D17: =YEAR(A17) -> 2024 | E17: =WEEKDAY(A17,2) -> 2 | F17: =WEEKNUM(A17,2) - WEEKNUM(DATE(YEAR(A17),MONTH(A17),1),2) + 1 -> 4 | H17: 7800 | I17: BANAMEX | J17: DEPOSITO EQUIVOCADO QUE FUE REEMBOLSADO | M17: =VLOOKUP(J17,RECATALOGANDO!A:C,2,0) -> REEMBOLSO | N17: =VLOOKUP(M17,RECATALOGANDO!B:C,2,0) -> DINERO DEVUELTO A ORIGEN | O17: NO ES INGRESO
A18: 45589 | B18: =DAY(A18) -> 24 | C18: =MONTH(A18) -> 10 | D18: =YEAR(A18) -> 2024 | E18: =WEEKDAY(A18,2) -> 4 | F18: =WEEKNUM(A18,2) - WEEKNUM(DATE(YEAR(A18),MONTH(A18),1),2) + 1 -> 4 | H18: 1340 | I18: BANAMEX | J18: DEVOLUCIÓN SPEI | M18: =VLOOKUP(J18,RECATALOGANDO!A:C,2,0) -> REEMBOLSO | N18: =VLOOKUP(M18,RECATALOGANDO!B:C,2,0) -> DINERO DEVUELTO A ORIGEN | O18: NO ES INGRESO
A19: 45602 | B19: =DAY(A19) -> 6 | C19: =MONTH(A19) -> 11 | D19: =YEAR(A19) -> 2024 | E19: =WEEKDAY(A19,2) -> 3 | F19: =WEEKNUM(A19,2) - WEEKNUM(DATE(YEAR(A19),MONTH(A19),1),2) + 1 -> 2 | H19: 226309.64 | I19: BBVA | J19: DEPOSITO PENSION ALIMENTICIA | M19: =VLOOKUP(J19,RECATALOGANDO!A:C,2,0) -> PENSION ALIMENTICIA | N19: =VLOOKUP(M19,RECATALOGANDO!B:C,2,0) -> PENSION | O19: NO ES INGRESO
A20: 45693 | B20: =DAY(A20) -> 5 | C20: =MONTH(A20) -> 2 | D20: =YEAR(A20) -> 2025 | E20: =WEEKDAY(A20,2) -> 3 | F20: =WEEKNUM(A20,2) - WEEKNUM(DATE(YEAR(A20),MONTH(A20),1),2) + 1 -> 2 | H20: 676.46 | I20: BANAMEX | J20: ABONO POR REEMBOLSO POR CARGO NO RECONOCIDO | M20: =VLOOKUP(J20,RECATALOGANDO!A:C,2,0) -> REEMBOLSO | N20: =VLOOKUP(M20,RECATALOGANDO!B:C,2,0) -> DINERO DEVUELTO A ORIGEN | O20: NO ES INGRESO
A21: 45695 | B21: =DAY(A21) -> 7 | C21: =MONTH(A21) -> 2 | D21: =YEAR(A21) -> 2025 | E21: =WEEKDAY(A21,2) -> 5 | F21: =WEEKNUM(A21,2) - WEEKNUM(DATE(YEAR(A21),MONTH(A21),1),2) + 1 -> 2 | H21: 676.46 | I21: BANAMEX | J21: ABONO POR REEMBOLSO POR CARGO NO RECONOCIDO | M21: =VLOOKUP(J21,RECATALOGANDO!A:C,2,0) -> REEMBOLSO | N21: =VLOOKUP(M21,RECATALOGANDO!B:C,2,0) -> DINERO DEVUELTO A ORIGEN | O21: NO ES INGRESO
A22: 45698 | B22: =DAY(A22) -> 10 | C22: =MONTH(A22) -> 2 | D22: =YEAR(A22) -> 2025 | E22: =WEEKDAY(A22,2) -> 1 | F22: =WEEKNUM(A22,2) - WEEKNUM(DATE(YEAR(A22),MONTH(A22),1),2) + 1 -> 3 | H22: 676.46 | I22: BANAMEX | J22: ABONO POR REEMBOLSO POR CARGO NO RECONOCIDO | M22: =VLOOKUP(J22,RECATALOGANDO!A:C,2,0) -> REEMBOLSO | N22: =VLOOKUP(M22,RECATALOGANDO!B:C,2,0) -> DINERO DEVUELTO A ORIGEN | O22: NO ES INGRESO
A23: 44930 | B23: =DAY(A23) -> 4 | C23: =MONTH(A23) -> 1 | D23: =YEAR(A23) -> 2023 | E23: =WEEKDAY(A23,2) -> 3 | F23: =WEEKNUM(A23,2) - WEEKNUM(DATE(YEAR(A23),MONTH(A23),1),2) + 1 -> 2 | H23: 1000 | I23: BANAMEX | J23: TRANFERENCIA ENTRE CUENTAS | M23: =VLOOKUP(J23,RECATALOGANDO!A:C,2,0) -> TRANSFERENCIA ENTRE CUENTAS | N23: =VLOOKUP(M23,RECATALOGANDO!B:C,2,0) -> TRANSFERENCIAS | O23: TRANSFERENCIAS
A24: 44941 | B24: =DAY(A24) -> 15 | C24: =MONTH(A24) -> 1 | D24: =YEAR(A24) -> 2023 | E24: =WEEKDAY(A24,2) -> 7 | F24: =WEEKNUM(A24,2) - WEEKNUM(DATE(YEAR(A24),MONTH(A24),1),2) + 1 -> 3 | H24: 200 | I24: BBVA | J24: TRANFERENCIA ENTRE CUENTAS | M24: =VLOOKUP(J24,RECATALOGANDO!A:C,2,0) -> TRANSFERENCIA ENTRE CUENTAS | N24: =VLOOKUP(M24,RECATALOGANDO!B:C,2,0) -> TRANSFERENCIAS | O24: TRANSFERENCIAS
A25: 44956 | B25: =DAY(A25) -> 30 | C25: =MONTH(A25) -> 1 | D25: =YEAR(A25) -> 2023 | E25: =WEEKDAY(A25,2) -> 1 | F25: =WEEKNUM(A25,2) - WEEKNUM(DATE(YEAR(A25),MONTH(A25),1),2) + 1 -> 6 | G25: 2 | H25: 700 | I25: BBVA | J25: TRANSFERENCIA ENTRE CUENTAS | M25: =VLOOKUP(J25,RECATALOGANDO!A:C,2,0) -> TRANSFERENCIA ENTRE CUENTAS | N25: =VLOOKUP(M25,RECATALOGANDO!B:C,2,0) -> TRANSFERENCIAS | O25: TRANSFERENCIAS
A26: 44956 | B26: =DAY(A26) -> 30 | C26: =MONTH(A26) -> 1 | D26: =YEAR(A26) -> 2023 | E26: =WEEKDAY(A26,2) -> 1 | F26: =WEEKNUM(A26,2) - WEEKNUM(DATE(YEAR(A26),MONTH(A26),1),2) + 1 -> 6 | G26: 2 | H26: 700 | I26: BBVA | J26: TRANSFERENCIA ENTRE CUENTAS | M26: =VLOOKUP(J26,RECATALOGANDO!A:C,2,0) -> TRANSFERENCIA ENTRE CUENTAS | N26: =VLOOKUP(M26,RECATALOGANDO!B:C,2,0) -> TRANSFERENCIAS | O26: TRANSFERENCIAS
A27: 44958 | B27: =DAY(A27) -> 1 | C27: =MONTH(A27) -> 2 | D27: =YEAR(A27) -> 2023 | E27: =WEEKDAY(A27,2) -> 3 | F27: =WEEKNUM(A27,2) - WEEKNUM(DATE(YEAR(A27),MONTH(A27),1),2) + 1 -> 1 | H27: 1000 | I27: BANAMEX | J27: TRANSFERENCIA ENTRE CUENTAS | M27: =VLOOKUP(J27,RECATALOGANDO!A:C,2,0) -> TRANSFERENCIA ENTRE CUENTAS | N27: =VLOOKUP(M27,RECATALOGANDO!B:C,2,0) -> TRANSFERENCIAS | O27: TRANSFERENCIAS
A28: 44958 | B28: =DAY(A28) -> 1 | C28: =MONTH(A28) -> 2 | D28: =YEAR(A28) -> 2023 | E28: =WEEKDAY(A28,2) -> 3 | F28: =WEEKNUM(A28,2) - WEEKNUM(DATE(YEAR(A28),MONTH(A28),1),2) + 1 -> 1 | H28: 1000 | I28: BANAMEX | J28: TRANSFERENCIA ENTRE CUENTAS | M28: =VLOOKUP(J28,RECATALOGANDO!A:C,2,0) -> TRANSFERENCIA ENTRE CUENTAS | N28: =VLOOKUP(M28,RECATALOGANDO!B:C,2,0) -> TRANSFERENCIAS | O28: TRANSFERENCIAS
A29: 44965 | B29: =DAY(A29) -> 8 | C29: =MONTH(A29) -> 2 | D29: =YEAR(A29) -> 2023 | E29: =WEEKDAY(A29,2) -> 3 | F29: =WEEKNUM(A29,2) - WEEKNUM(DATE(YEAR(A29),MONTH(A29),1),2) + 1 -> 2 | H29: 500 | I29: BANAMEX | J29: TRANSFERENCIA ENTRE CUENTAS | M29: =VLOOKUP(J29,RECATALOGANDO!A:C,2,0) -> TRANSFERENCIA ENTRE CUENTAS | N29: =VLOOKUP(M29,RECATALOGANDO!B:C,2,0) -> TRANSFERENCIAS | O29: TRANSFERENCIAS
A30: 44965 | B30: =DAY(A30) -> 8 | C30: =MONTH(A30) -> 2 | D30: =YEAR(A30) -> 2023 | E30: =WEEKDAY(A30,2) -> 3 | F30: =WEEKNUM(A30,2) - WEEKNUM(DATE(YEAR(A30),MONTH(A30),1),2) + 1 -> 2 | H30: 500 | I30: BANAMEX | J30: TRANSFERENCIA ENTRE CUENTAS | M30: =VLOOKUP(J30,RECATALOGANDO!A:C,2,0) -> TRANSFERENCIA ENTRE CUENTAS | N30: =VLOOKUP(M30,RECATALOGANDO!B:C,2,0) -> TRANSFERENCIAS | O30: TRANSFERENCIAS
A31: 44970 | B31: =DAY(A31) -> 13 | C31: =MONTH(A31) -> 2 | D31: =YEAR(A31) -> 2023 | E31: =WEEKDAY(A31,2) -> 1 | F31: =WEEKNUM(A31,2) - WEEKNUM(DATE(YEAR(A31),MONTH(A31),1),2) + 1 -> 3 | H31: 1700 | I31: BANAMEX | J31: TRANSFERENCIA ENTRE CUENTAS | M31: =VLOOKUP(J31,RECATALOGANDO!A:C,2,0) -> TRANSFERENCIA ENTRE CUENTAS | N31: =VLOOKUP(M31,RECATALOGANDO!B:C,2,0) -> TRANSFERENCIAS | O31: TRANSFERENCIAS
A32: 44970 | B32: =DAY(A32) -> 13 | C32: =MONTH(A32) -> 2 | D32: =YEAR(A32) -> 2023 | E32: =WEEKDAY(A32,2) -> 1 | F32: =WEEKNUM(A32,2) - WEEKNUM(DATE(YEAR(A32),MONTH(A32),1),2) + 1 -> 3 | H32: 1700 | I32: BANAMEX | J32: TRANSFERENCIA ENTRE CUENTAS | M32: =VLOOKUP(J32,RECATALOGANDO!A:C,2,0) -> TRANSFERENCIA ENTRE CUENTAS | N32: =VLOOKUP(M32,RECATALOGANDO!B:C,2,0) -> TRANSFERENCIAS | O32: TRANSFERENCIAS
A33: 44974 | B33: =DAY(A33) -> 17 | C33: =MONTH(A33) -> 2 | D33: =YEAR(A33) -> 2023 | E33: =WEEKDAY(A33,2) -> 5 | F33: =WEEKNUM(A33,2) - WEEKNUM(DATE(YEAR(A33),MONTH(A33),1),2) + 1 -> 3 | H33: 900 | I33: BBVA | J33: TRANSFERENCIA ENTRE CUENTAS | M33: =VLOOKUP(J33,RECATALOGANDO!A:C,2,0) -> TRANSFERENCIA ENTRE CUENTAS | N33: =VLOOKUP(M33,RECATALOGANDO!B:C,2,0) -> TRANSFERENCIAS | O33: TRANSFERENCIAS
A34: 44974 | B34: =DAY(A34) -> 17 | C34: =MONTH(A34) -> 2 | D34: =YEAR(A34) -> 2023 | E34: =WEEKDAY(A34,2) -> 5 | F34: =WEEKNUM(A34,2) - WEEKNUM(DATE(YEAR(A34),MONTH(A34),1),2) + 1 -> 3 | H34: 900 | I34: BBVA | J34: TRANSFERENCIA ENTRE CUENTAS | M34: =VLOOKUP(J34,RECATALOGANDO!A:C,2,0) -> TRANSFERENCIA ENTRE CUENTAS | N34: =VLOOKUP(M34,RECATALOGANDO!B:C,2,0) -> TRANSFERENCIAS | O34: TRANSFERENCIAS
A35: 44982 | B35: =DAY(A35) -> 25 | C35: =MONTH(A35) -> 2 | D35: =YEAR(A35) -> 2023 | E35: =WEEKDAY(A35,2) -> 6 | F35: =WEEKNUM(A35,2) - WEEKNUM(DATE(YEAR(A35),MONTH(A35),1),2) + 1 -> 4 | H35: 500 | I35: BBVA | J35: TRANSFERENCIA ENTRE CUENTAS | M35: =VLOOKUP(J35,RECATALOGANDO!A:C,2,0) -> TRANSFERENCIA ENTRE CUENTAS | N35: =VLOOKUP(M35,RECATALOGANDO!B:C,2,0) -> TRANSFERENCIAS | O35: TRANSFERENCIAS
A36: 44982 | B36: =DAY(A36) -> 25 | C36: =MONTH(A36) -> 2 | D36: =YEAR(A36) -> 2023 | E36: =WEEKDAY(A36,2) -> 6 | F36: =WEEKNUM(A36,2) - WEEKNUM(DATE(YEAR(A36),MONTH(A36),1),2) + 1 -> 4 | H36: 500 | I36: BBVA | J36: TRANSFERENCIA ENTRE CUENTAS | M36: =VLOOKUP(J36,RECATALOGANDO!A:C,2,0) -> TRANSFERENCIA ENTRE CUENTAS | N36: =VLOOKUP(M36,RECATALOGANDO!B:C,2,0) -> TRANSFERENCIAS | O36: TRANSFERENCIAS
A37: 44988 | B37: =DAY(A37) -> 3 | C37: =MONTH(A37) -> 3 | D37: =YEAR(A37) -> 2023 | E37: =WEEKDAY(A37,2) -> 5 | F37: =WEEKNUM(A37,2) - WEEKNUM(DATE(YEAR(A37),MONTH(A37),1),2) + 1 -> 1 | H37: 800 | I37: BBVA | J37: TRANSFERENCIA ENTRE CUENTAS | M37: =VLOOKUP(J37,RECATALOGANDO!A:C,2,0) -> TRANSFERENCIA ENTRE CUENTAS | N37: =VLOOKUP(M37,RECATALOGANDO!B:C,2,0) -> TRANSFERENCIAS | O37: TRANSFERENCIAS
A38: 44995 | B38: =DAY(A38) -> 10 | C38: =MONTH(A38) -> 3 | D38: =YEAR(A38) -> 2023 | E38: =WEEKDAY(A38,2) -> 5 | F38: =WEEKNUM(A38,2) - WEEKNUM(DATE(YEAR(A38),MONTH(A38),1),2) + 1 -> 2 | H38: 100 | I38: BANAMEX | J38: TRANSFERENCIA ENTRE CUENTAS | M38: =VLOOKUP(J38,RECATALOGANDO!A:C,2,0) -> TRANSFERENCIA ENTRE CUENTAS | N38: =VLOOKUP(M38,RECATALOGANDO!B:C,2,0) -> TRANSFERENCIAS | O38: TRANSFERENCIAS
... A72: 45217 | B72: =DAY(A72) -> 18 | C72: =MONTH(A72) -> 10 | D72: =YEAR(A72) -> 2023 | E72: =WEEKDAY(A72,2) -> 3 | F72: =WEEKNUM(A72,2) - WEEKNUM(DATE(YEAR(A72),MONTH(A72),1),2) + 1 -> 4 | H72: 2100 | I72: BANAMEX | J72: TRANSFERENCIA ENTRE CUENTAS | M72: =VLOOKUP(J72,RECATALOGANDO!A:C,2,0) -> TRANSFERENCIA ENTRE CUENTAS | N72: =VLOOKUP(M72,RECATALOGANDO!B:C,2,0) -> TRANSFERENCIAS | O72: TRANSFERENCIAS
A73: 45229 | B73: =DAY(A73) -> 30 | C73: =MONTH(A73) -> 10 | D73: =YEAR(A73) -> 2023 | E73: =WEEKDAY(A73,2) -> 1 | F73: =WEEKNUM(A73,2) - WEEKNUM(DATE(YEAR(A73),MONTH(A73),1),2) + 1 -> 6 | G73: 2 | H73: 565 | I73: BANAMEX | J73: TRANSFERENCIA ENTRE CUENTAS | M73: =VLOOKUP(J73,RECATALOGANDO!A:C,2,0) -> TRANSFERENCIA ENTRE CUENTAS | N73: =VLOOKUP(M73,RECATALOGANDO!B:C,2,0) -> TRANSFERENCIAS | O73: TRANSFERENCIAS
A74: 45237 | B74: =DAY(A74) -> 7 | C74: =MONTH(A74) -> 11 | D74: =YEAR(A74) -> 2023 | E74: =WEEKDAY(A74,2) -> 2 | F74: =WEEKNUM(A74,2) - WEEKNUM(DATE(YEAR(A74),MONTH(A74),1),2) + 1 -> 2 | H74: 2375 | I74: BBVA | J74: DEPOSITO FAMILIAR | M74: =VLOOKUP(J74,RECATALOGANDO!A:C,2,0) -> TRANSFERENCIA FAMILIAR | N74: =VLOOKUP(M74,RECATALOGANDO!B:C,2,0) -> TRANSFERENCIAS | O74: TRANSFERENCIAS
A75: 45251 | B75: =DAY(A75) -> 21 | C75: =MONTH(A75) -> 11 | D75: =YEAR(A75) -> 2023 | E75: =WEEKDAY(A75,2) -> 2 | F75: =WEEKNUM(A75,2) - WEEKNUM(DATE(YEAR(A75),MONTH(A75),1),2) + 1 -> 4 | H75: 300 | I75: BANAMEX | J75: TRANSFERENCIA ENTRE CUENTAS | M75: =VLOOKUP(J75,RECATALOGANDO!A:C,2,0) -> TRANSFERENCIA ENTRE CUENTAS | N75: =VLOOKUP(M75,RECATALOGANDO!B:C,2,0) -> TRANSFERENCIAS | O75: TRANSFERENCIAS
A76: 45252 | B76: =DAY(A76) -> 22 | C76: =MONTH(A76) -> 11 | D76: =YEAR(A76) -> 2023 | E76: =WEEKDAY(A76,2) -> 3 | F76: =WEEKNUM(A76,2) - WEEKNUM(DATE(YEAR(A76),MONTH(A76),1),2) + 1 -> 4 | H76: 1000 | I76: BANAMEX | J76: TRANSFERENCIA ENTRE CUENTAS | M76: =VLOOKUP(J76,RECATALOGANDO!A:C,2,0) -> TRANSFERENCIA ENTRE CUENTAS | N76: =VLOOKUP(M76,RECATALOGANDO!B:C,2,0) -> TRANSFERENCIAS | O76: TRANSFERENCIAS
A77: 45253 | B77: =DAY(A77) -> 23 | C77: =MONTH(A77) -> 11 | D77: =YEAR(A77) -> 2023 | E77: =WEEKDAY(A77,2) -> 4 | F77: =WEEKNUM(A77,2) - WEEKNUM(DATE(YEAR(A77),MONTH(A77),1),2) + 1 -> 4 | H77: 300 | I77: BANAMEX | J77: TRANSFERENCIA ENTRE CUENTAS | M77: =VLOOKUP(J77,RECATALOGANDO!A:C,2,0) -> TRANSFERENCIA ENTRE CUENTAS | N77: =VLOOKUP(M77,RECATALOGANDO!B:C,2,0) -> TRANSFERENCIAS | O77: TRANSFERENCIAS
A78: 45253 | B78: =DAY(A78) -> 23 | C78: =MONTH(A78) -> 11 | D78: =YEAR(A78) -> 2023 | E78: =WEEKDAY(A78,2) -> 4 | F78: =WEEKNUM(A78,2) - WEEKNUM(DATE(YEAR(A78),MONTH(A78),1),2) + 1 -> 4 | H78: 950 | I78: BANAMEX | J78: TRANSFERENCIA ENTRE CUENTAS | M78: =VLOOKUP(J78,RECATALOGANDO!A:C,2,0) -> TRANSFERENCIA ENTRE CUENTAS | N78: =VLOOKUP(M78,RECATALOGANDO!B:C,2,0) -> TRANSFERENCIAS | O78: TRANSFERENCIAS
A79: 45269 | B79: =DAY(A79) -> 9 | C79: =MONTH(A79) -> 12 | D79: =YEAR(A79) -> 2023 | E79: =WEEKDAY(A79,2) -> 6 | F79: =WEEKNUM(A79,2) - WEEKNUM(DATE(YEAR(A79),MONTH(A79),1),2) + 1 -> 2 | H79: 800 | I79: BBVA | J79: TRANSFERENCIA ENTRE CUENTAS | M79: =VLOOKUP(J79,RECATALOGANDO!A:C,2,0) -> TRANSFERENCIA ENTRE CUENTAS | N79: =VLOOKUP(M79,RECATALOGANDO!B:C,2,0) -> TRANSFERENCIAS | O79: TRANSFERENCIAS
A80: 45269 | B80: =DAY(A80) -> 9 | C80: =MONTH(A80) -> 12 | D80: =YEAR(A80) -> 2023 | E80: =WEEKDAY(A80,2) -> 6 | F80: =WEEKNUM(A80,2) - WEEKNUM(DATE(YEAR(A80),MONTH(A80),1),2) + 1 -> 2 | H80: 3000 | I80: BBVA | J80: TRANSFERENCIA ENTRE CUENTAS | M80: =VLOOKUP(J80,RECATALOGANDO!A:C,2,0) -> TRANSFERENCIA ENTRE CUENTAS | N80: =VLOOKUP(M80,RECATALOGANDO!B:C,2,0) -> TRANSFERENCIAS | O80: TRANSFERENCIAS
A81: 45271 | B81: =DAY(A81) -> 11 | C81: =MONTH(A81) -> 12 | D81: =YEAR(A81) -> 2023 | E81: =WEEKDAY(A81,2) -> 1 | F81: =WEEKNUM(A81,2) - WEEKNUM(DATE(YEAR(A81),MONTH(A81),1),2) + 1 -> 3 | H81: 1000 | I81: BBVA | J81: DEPOSITO FAMILIAR | M81: =VLOOKUP(J81,RECATALOGANDO!A:C,2,0) -> TRANSFERENCIA FAMILIAR | N81: =VLOOKUP(M81,RECATALOGANDO!B:C,2,0) -> TRANSFERENCIAS | O81: TRANSFERENCIAS
A82: 45274 | B82: =DAY(A82) -> 14 | C82: =MONTH(A82) -> 12 | D82: =YEAR(A82) -> 2023 | E82: =WEEKDAY(A82,2) -> 4 | F82: =WEEKNUM(A82,2) - WEEKNUM(DATE(YEAR(A82),MONTH(A82),1),2) + 1 -> 3 | H82: 500 | I82: BBVA | J82: DEPOSITO FAMILIAR | M82: =VLOOKUP(J82,RECATALOGANDO!A:C,2,0) -> TRANSFERENCIA FAMILIAR | N82: =VLOOKUP(M82,RECATALOGANDO!B:C,2,0) -> TRANSFERENCIAS | O82: TRANSFERENCIAS
A83: 45275 | B83: =DAY(A83) -> 15 | C83: =MONTH(A83) -> 12 | D83: =YEAR(A83) -> 2023 | E83: =WEEKDAY(A83,2) -> 5 | F83: =WEEKNUM(A83,2) - WEEKNUM(DATE(YEAR(A83),MONTH(A83),1),2) + 1 -> 3 | G83: 1 | H83: 800 | I83: BBVA | J83: TRANSFERENCIA ENTRE CUENTAS | M83: =VLOOKUP(J83,RECATALOGANDO!A:C,2,0) -> TRANSFERENCIA ENTRE CUENTAS | N83: =VLOOKUP(M83,RECATALOGANDO!B:C,2,0) -> TRANSFERENCIAS | O83: TRANSFERENCIAS
A84: 45275 | B84: =DAY(A84) -> 15 | C84: =MONTH(A84) -> 12 | D84: =YEAR(A84) -> 2023 | E84: =WEEKDAY(A84,2) -> 5 | F84: =WEEKNUM(A84,2) - WEEKNUM(DATE(YEAR(A84),MONTH(A84),1),2) + 1 -> 3 | G84: 1 | H84: 1600 | I84: BBVA | J84: DEPOSITO FAMILIAR | M84: =VLOOKUP(J84,RECATALOGANDO!A:C,2,0) -> TRANSFERENCIA FAMILIAR | N84: =VLOOKUP(M84,RECATALOGANDO!B:C,2,0) -> TRANSFERENCIAS | O84: TRANSFERENCIAS
A85: 45276 | B85: =DAY(A85) -> 16 | C85: =MONTH(A85) -> 12 | D85: =YEAR(A85) -> 2023 | E85: =WEEKDAY(A85,2) -> 6 | F85: =WEEKNUM(A85,2) - WEEKNUM(DATE(YEAR(A85),MONTH(A85),1),2) + 1 -> 3 | H85: 650 | I85: BBVA | J85: DEPOSITO FAMILIAR | M85: =VLOOKUP(J85,RECATALOGANDO!A:C,2,0) -> TRANSFERENCIA FAMILIAR | N85: =VLOOKUP(M85,RECATALOGANDO!B:C,2,0) -> TRANSFERENCIAS | O85: TRANSFERENCIAS
A86: 45287 | B86: =DAY(A86) -> 27 | C86: =MONTH(A86) -> 12 | D86: =YEAR(A86) -> 2023 | E86: =WEEKDAY(A86,2) -> 3 | F86: =WEEKNUM(A86,2) - WEEKNUM(DATE(YEAR(A86),MONTH(A86),1),2) + 1 -> 5 | H86: 500 | I86: BBVA | J86: TRANSFERENCIA ENTRE CUENTAS | M86: =VLOOKUP(J86,RECATALOGANDO!A:C,2,0) -> TRANSFERENCIA ENTRE CUENTAS | N86: =VLOOKUP(M86,RECATALOGANDO!B:C,2,0) -> TRANSFERENCIAS | O86: TRANSFERENCIAS
A87: 45324 | B87: =DAY(A87) -> 2 | C87: =MONTH(A87) -> 2 | D87: =YEAR(A87) -> 2024 | E87: =WEEKDAY(A87,2) -> 5 | F87: =WEEKNUM(A87,2) - WEEKNUM(DATE(YEAR(A87),MONTH(A87),1),2) + 1 -> 1 | H87: 350 | I87: BBVA | J87: ENTRE CUENTAS | M87: =VLOOKUP(J87,RECATALOGANDO!A:C,2,0) -> TRANSFERENCIA ENTRE CUENTAS | N87: =VLOOKUP(M87,RECATALOGANDO!B:C,2,0) -> TRANSFERENCIAS | O87: TRANSFERENCIAS
A88: 45330 | B88: =DAY(A88) -> 8 | C88: =MONTH(A88) -> 2 | D88: =YEAR(A88) -> 2024 | E88: =WEEKDAY(A88,2) -> 4 | F88: =WEEKNUM(A88,2) - WEEKNUM(DATE(YEAR(A88),MONTH(A88),1),2) + 1 -> 2 | H88: 960 | I88: BBVA | J88: TRANSFERENCIA FAMILIAR | M88: =VLOOKUP(J88,RECATALOGANDO!A:C,2,0) -> TRANSFERENCIA FAMILIAR | N88: =VLOOKUP(M88,RECATALOGANDO!B:C,2,0) -> TRANSFERENCIAS | O88: TRANSFERENCIAS
A89: 45336 | B89: =DAY(A89) -> 14 | C89: =MONTH(A89) -> 2 | D89: =YEAR(A89) -> 2024 | E89: =WEEKDAY(A89,2) -> 3 | F89: =WEEKNUM(A89,2) - WEEKNUM(DATE(YEAR(A89),MONTH(A89),1),2) + 1 -> 3 | H89: 1000 | I89: BANAMEX | J89: ENTRE CUENTAS | M89: =VLOOKUP(J89,RECATALOGANDO!A:C,2,0) -> TRANSFERENCIA ENTRE CUENTAS | N89: =VLOOKUP(M89,RECATALOGANDO!B:C,2,0) -> TRANSFERENCIAS | O89: TRANSFERENCIAS
A90: 45337 | B90: =DAY(A90) -> 15 | C90: =MONTH(A90) -> 2 | D90: =YEAR(A90) -> 2024 | E90: =WEEKDAY(A90,2) -> 4 | F90: =WEEKNUM(A90,2) - WEEKNUM(DATE(YEAR(A90),MONTH(A90),1),2) + 1 -> 3 | G90: 1 | H90: 800 | I90: BBVA | J90: TRANSFERENCIA FAMILIAR | M90: =VLOOKUP(J90,RECATALOGANDO!A:C,2,0) -> TRANSFERENCIA FAMILIAR | N90: =VLOOKUP(M90,RECATALOGANDO!B:C,2,0) -> TRANSFERENCIAS | O90: TRANSFERENCIAS
A91: 45338 | B91: =DAY(A91) -> 16 | C91: =MONTH(A91) -> 2 | D91: =YEAR(A91) -> 2024 | E91: =WEEKDAY(A91,2) -> 5 | F91: =WEEKNUM(A91,2) - WEEKNUM(DATE(YEAR(A91),MONTH(A91),1),2) + 1 -> 3 | H91: 324 | I91: BANAMEX | J91: ENTRE CUENTAS | M91: =VLOOKUP(J91,RECATALOGANDO!A:C,2,0) -> TRANSFERENCIA ENTRE CUENTAS | N91: =VLOOKUP(M91,RECATALOGANDO!B:C,2,0) -> TRANSFERENCIAS | O91: TRANSFERENCIAS
A92: 45338 | B92: =DAY(A92) -> 16 | C92: =MONTH(A92) -> 2 | D92: =YEAR(A92) -> 2024 | E92: =WEEKDAY(A92,2) -> 5 | F92: =WEEKNUM(A92,2) - WEEKNUM(DATE(YEAR(A92),MONTH(A92),1),2) + 1 -> 3 | H92: 2000 | I92: BANAMEX | J92: TRANSFERENCIA FAMILIAR | M92: =VLOOKUP(J92,RECATALOGANDO!A:C,2,0) -> TRANSFERENCIA FAMILIAR | N92: =VLOOKUP(M92,RECATALOGANDO!B:C,2,0) -> TRANSFERENCIAS | O92: TRANSFERENCIAS
A93: 45338 | B93: =DAY(A93) -> 16 | C93: =MONTH(A93) -> 2 | D93: =YEAR(A93) -> 2024 | E93: =WEEKDAY(A93,2) -> 5 | F93: =WEEKNUM(A93,2) - WEEKNUM(DATE(YEAR(A93),MONTH(A93),1),2) + 1 -> 3 | H93: 2900 | I93: BBVA | J93: ENTRE CUENTAS | M93: =VLOOKUP(J93,RECATALOGANDO!A:C,2,0) -> TRANSFERENCIA ENTRE CUENTAS | N93: =VLOOKUP(M93,RECATALOGANDO!B:C,2,0) -> TRANSFERENCIAS | O93: TRANSFERENCIAS
A94: 45342 | B94: =DAY(A94) -> 20 | C94: =MONTH(A94) -> 2 | D94: =YEAR(A94) -> 2024 | E94: =WEEKDAY(A94,2) -> 2 | F94: =WEEKNUM(A94,2) - WEEKNUM(DATE(YEAR(A94),MONTH(A94),1),2) + 1 -> 4 | H94: 1100 | I94: BANAMEX | J94: ENTRE CUENTAS | M94: =VLOOKUP(J94,RECATALOGANDO!A:C,2,0) -> TRANSFERENCIA ENTRE CUENTAS | N94: =VLOOKUP(M94,RECATALOGANDO!B:C,2,0) -> TRANSFERENCIAS | O94: TRANSFERENCIAS
A95: 45352 | B95: =DAY(A95) -> 1 | C95: =MONTH(A95) -> 3 | D95: =YEAR(A95) -> 2024 | E95: =WEEKDAY(A95,2) -> 5 | F95: =WEEKNUM(A95,2) - WEEKNUM(DATE(YEAR(A95),MONTH(A95),1),2) + 1 -> 1 | H95: 300 | I95: BANAMEX | J95: ENTRE CUENTAS | M95: =VLOOKUP(J95,RECATALOGANDO!A:C,2,0) -> TRANSFERENCIA ENTRE CUENTAS | N95: =VLOOKUP(M95,RECATALOGANDO!B:C,2,0) -> TRANSFERENCIAS | O95: TRANSFERENCIAS
A96: 45355 | B96: =DAY(A96) -> 4 | C96: =MONTH(A96) -> 3 | D96: =YEAR(A96) -> 2024 | E96: =WEEKDAY(A96,2) -> 1 | F96: =WEEKNUM(A96,2) - WEEKNUM(DATE(YEAR(A96),MONTH(A96),1),2) + 1 -> 2 | H96: 700 | I96: BBVA | J96: DEPOSITO FAMILIAR | M96: =VLOOKUP(J96,RECATALOGANDO!A:C,2,0) -> TRANSFERENCIA FAMILIAR | N96: =VLOOKUP(M96,RECATALOGANDO!B:C,2,0) -> TRANSFERENCIAS | O96: TRANSFERENCIAS
A97: 45355 | B97: =DAY(A97) -> 4 | C97: =MONTH(A97) -> 3 | D97: =YEAR(A97) -> 2024 | E97: =WEEKDAY(A97,2) -> 1 | F97: =WEEKNUM(A97,2) - WEEKNUM(DATE(YEAR(A97),MONTH(A97),1),2) + 1 -> 2 | H97: 2400 | I97: BANAMEX | J97: DEPOSITO FAMILIAR | M97: =VLOOKUP(J97,RECATALOGANDO!A:C,2,0) -> TRANSFERENCIA FAMILIAR | N97: =VLOOKUP(M97,RECATALOGANDO!B:C,2,0) -> TRANSFERENCIAS | O97: TRANSFERENCIAS
A98: 45357 | B98: =DAY(A98) -> 6 | C98: =MONTH(A98) -> 3 | D98: =YEAR(A98) -> 2024 | E98: =WEEKDAY(A98,2) -> 3 | F98: =WEEKNUM(A98,2) - WEEKNUM(DATE(YEAR(A98),MONTH(A98),1),2) + 1 -> 2 | H98: 450 | I98: BBVA | J98: ENTRE CUENTAS | M98: =VLOOKUP(J98,RECATALOGANDO!A:C,2,0) -> TRANSFERENCIA ENTRE CUENTAS | N98: =VLOOKUP(M98,RECATALOGANDO!B:C,2,0) -> TRANSFERENCIAS | O98: TRANSFERENCIAS
A99: 45357 | B99: =DAY(A99) -> 6 | C99: =MONTH(A99) -> 3 | D99: =YEAR(A99) -> 2024 | E99: =WEEKDAY(A99,2) -> 3 | F99: =WEEKNUM(A99,2) - WEEKNUM(DATE(YEAR(A99),MONTH(A99),1),2) + 1 -> 2 | H99: 2750 | I99: BBVA | J99: DEPOSITO FAMILIAR | M99: =VLOOKUP(J99,RECATALOGANDO!A:C,2,0) -> TRANSFERENCIA FAMILIAR | N99: =VLOOKUP(M99,RECATALOGANDO!B:C,2,0) -> TRANSFERENCIAS | O99: TRANSFERENCIAS
A100: 45365 | B100: =DAY(A100) -> 14 | C100: =MONTH(A100) -> 3 | D100: =YEAR(A100) -> 2024 | E100: =WEEKDAY(A100,2) -> 4 | F100: =WEEKNUM(A100,2) - WEEKNUM(DATE(YEAR(A100),MONTH(A100),1),2) + 1 -> 3 | H100: 2200 | I100: BBVA | J100: DEPOSITO FAMILIAR | M100: =VLOOKUP(J100,RECATALOGANDO!A:C,2,0) -> TRANSFERENCIA FAMILIAR | N100: =VLOOKUP(M100,RECATALOGANDO!B:C,2,0) -> TRANSFERENCIAS | O100: TRANSFERENCIAS
A101: 45369 | B101: =DAY(A101) -> 18 | C101: =MONTH(A101) -> 3 | D101: =YEAR(A101) -> 2024 | E101: =WEEKDAY(A101,2) -> 1 | F101: =WEEKNUM(A101,2) - WEEKNUM(DATE(YEAR(A101),MONTH(A101),1),2) + 1 -> 4 | H101: 500 | I101: BBVA | J101: DEPOSITO FAMILIAR | M101: =VLOOKUP(J101,RECATALOGANDO!A:C,2,0) -> TRANSFERENCIA FAMILIAR | N101: =VLOOKUP(M101,RECATALOGANDO!B:C,2,0) -> TRANSFERENCIAS | O101: TRANSFERENCIAS
A102: 45376 | B102: =DAY(A102) -> 25 | C102: =MONTH(A102) -> 3 | D102: =YEAR(A102) -> 2024 | E102: =WEEKDAY(A102,2) -> 1 | F102: =WEEKNUM(A102,2) - WEEKNUM(DATE(YEAR(A102),MONTH(A102),1),2) + 1 -> 5 | H102: 200 | I102: BANAMEX | J102: ENTRE CUENTAS | M102: =VLOOKUP(J102,RECATALOGANDO!A:C,2,0) -> TRANSFERENCIA ENTRE CUENTAS | N102: =VLOOKUP(M102,RECATALOGANDO!B:C,2,0) -> TRANSFERENCIAS | O102: TRANSFERENCIAS
... A116: 45426 | B116: =DAY(A116) -> 14 | C116: =MONTH(A116) -> 5 | D116: =YEAR(A116) -> 2024 | E116: =WEEKDAY(A116,2) -> 2 | F116: =WEEKNUM(A116,2) - WEEKNUM(DATE(YEAR(A116),MONTH(A116),1),2) + 1 -> 3 | H116: 1500 | I116: BANAMEX | J116: ENTRE CUENTAS | M116: =VLOOKUP(J116,RECATALOGANDO!A:C,2,0) -> TRANSFERENCIA ENTRE CUENTAS | N116: =VLOOKUP(M116,RECATALOGANDO!B:C,2,0) -> TRANSFERENCIAS | O116: TRANSFERENCIAS
A117: 45427 | B117: =DAY(A117) -> 15 | C117: =MONTH(A117) -> 5 | D117: =YEAR(A117) -> 2024 | E117: =WEEKDAY(A117,2) -> 3 | F117: =WEEKNUM(A117,2) - WEEKNUM(DATE(YEAR(A117),MONTH(A117),1),2) + 1 -> 3 | G117: 1 | H117: 500 | I117: BANAMEX | J117: TRANSFERENCIA FAMILIAR | M117: =VLOOKUP(J117,RECATALOGANDO!A:C,2,0) -> TRANSFERENCIA FAMILIAR | N117: =VLOOKUP(M117,RECATALOGANDO!B:C,2,0) -> TRANSFERENCIAS | O117: TRANSFERENCIAS
A118: 45428 | B118: =DAY(A118) -> 16 | C118: =MONTH(A118) -> 5 | D118: =YEAR(A118) -> 2024 | E118: =WEEKDAY(A118,2) -> 4 | F118: =WEEKNUM(A118,2) - WEEKNUM(DATE(YEAR(A118),MONTH(A118),1),2) + 1 -> 3 | H118: 490 | I118: BBVA | J118: TRANSFERENCIA ENTRE CUENTAS | M118: =VLOOKUP(J118,RECATALOGANDO!A:C,2,0) -> TRANSFERENCIA ENTRE CUENTAS | N118: =VLOOKUP(M118,RECATALOGANDO!B:C,2,0) -> TRANSFERENCIAS | O118: TRANSFERENCIAS
A119: 45428 | B119: =DAY(A119) -> 16 | C119: =MONTH(A119) -> 5 | D119: =YEAR(A119) -> 2024 | E119: =WEEKDAY(A119,2) -> 4 | F119: =WEEKNUM(A119,2) - WEEKNUM(DATE(YEAR(A119),MONTH(A119),1),2) + 1 -> 3 | H119: 550 | I119: BANAMEX | J119: TRANSFERENCIA FAMILIAR | M119: =VLOOKUP(J119,RECATALOGANDO!A:C,2,0) -> TRANSFERENCIA FAMILIAR | N119: =VLOOKUP(M119,RECATALOGANDO!B:C,2,0) -> TRANSFERENCIAS | O119: TRANSFERENCIAS
A120: 45428 | B120: =DAY(A120) -> 16 | C120: =MONTH(A120) -> 5 | D120: =YEAR(A120) -> 2024 | E120: =WEEKDAY(A120,2) -> 4 | F120: =WEEKNUM(A120,2) - WEEKNUM(DATE(YEAR(A120),MONTH(A120),1),2) + 1 -> 3 | H120: 800 | I120: BANAMEX | J120: TRANSFERENCIA ENTRE CUENTAS | M120: =VLOOKUP(J120,RECATALOGANDO!A:C,2,0) -> TRANSFERENCIA ENTRE CUENTAS | N120: =VLOOKUP(M120,RECATALOGANDO!B:C,2,0) -> TRANSFERENCIAS | O120: TRANSFERENCIAS
A121: 45432 | B121: =DAY(A121) -> 20 | C121: =MONTH(A121) -> 5 | D121: =YEAR(A121) -> 2024 | E121: =WEEKDAY(A121,2) -> 1 | F121: =WEEKNUM(A121,2) - WEEKNUM(DATE(YEAR(A121),MONTH(A121),1),2) + 1 -> 4 | H121: 200 | I121: BANAMEX | J121: TRANSFERENCIA FAMILIAR | M121: =VLOOKUP(J121,RECATALOGANDO!A:C,2,0) -> TRANSFERENCIA FAMILIAR | N121: =VLOOKUP(M121,RECATALOGANDO!B:C,2,0) -> TRANSFERENCIAS | O121: TRANSFERENCIAS
A122: 45433 | B122: =DAY(A122) -> 21 | C122: =MONTH(A122) -> 5 | D122: =YEAR(A122) -> 2024 | E122: =WEEKDAY(A122,2) -> 2 | F122: =WEEKNUM(A122,2) - WEEKNUM(DATE(YEAR(A122),MONTH(A122),1),2) + 1 -> 4 | H122: 500 | I122: BBVA | J122: TRANSFERENCIA FAMILIAR | M122: =VLOOKUP(J122,RECATALOGANDO!A:C,2,0) -> TRANSFERENCIA FAMILIAR | N122: =VLOOKUP(M122,RECATALOGANDO!B:C,2,0) -> TRANSFERENCIAS | O122: TRANSFERENCIAS
A123: 45433 | B123: =DAY(A123) -> 21 | C123: =MONTH(A123) -> 5 | D123: =YEAR(A123) -> 2024 | E123: =WEEKDAY(A123,2) -> 2 | F123: =WEEKNUM(A123,2) - WEEKNUM(DATE(YEAR(A123),MONTH(A123),1),2) + 1 -> 4 | H123: 1500 | I123: BBVA | J123: TRANSFERENCIA ENTRE CUENTAS | M123: =VLOOKUP(J123,RECATALOGANDO!A:C,2,0) -> TRANSFERENCIA ENTRE CUENTAS | N123: =VLOOKUP(M123,RECATALOGANDO!B:C,2,0) -> TRANSFERENCIAS | O123: TRANSFERENCIAS
A124: 45434 | B124: =DAY(A124) -> 22 | C124: =MONTH(A124) -> 5 | D124: =YEAR(A124) -> 2024 | E124: =WEEKDAY(A124,2) -> 3 | F124: =WEEKNUM(A124,2) - WEEKNUM(DATE(YEAR(A124),MONTH(A124),1),2) + 1 -> 4 | H124: 500 | I124: BANAMEX | J124: TRANSFERENCIA FAMILIAR | M124: =VLOOKUP(J124,RECATALOGANDO!A:C,2,0) -> TRANSFERENCIA FAMILIAR | N124: =VLOOKUP(M124,RECATALOGANDO!B:C,2,0) -> TRANSFERENCIAS | O124: TRANSFERENCIAS
A125: 45434 | B125: =DAY(A125) -> 22 | C125: =MONTH(A125) -> 5 | D125: =YEAR(A125) -> 2024 | E125: =WEEKDAY(A125,2) -> 3 | F125: =WEEKNUM(A125,2) - WEEKNUM(DATE(YEAR(A125),MONTH(A125),1),2) + 1 -> 4 | H125: 614 | I125: BBVA | J125: TRANSFERENCIA FAMILIAR | M125: =VLOOKUP(J125,RECATALOGANDO!A:C,2,0) -> TRANSFERENCIA FAMILIAR | N125: =VLOOKUP(M125,RECATALOGANDO!B:C,2,0) -> TRANSFERENCIAS | O125: TRANSFERENCIAS
A126: 45436 | B126: =DAY(A126) -> 24 | C126: =MONTH(A126) -> 5 | D126: =YEAR(A126) -> 2024 | E126: =WEEKDAY(A126,2) -> 5 | F126: =WEEKNUM(A126,2) - WEEKNUM(DATE(YEAR(A126),MONTH(A126),1),2) + 1 -> 4 | H126: 250 | I126: BANAMEX | J126: TRANSFERENCIA ENTRE CUENTAS | M126: =VLOOKUP(J126,RECATALOGANDO!A:C,2,0) -> TRANSFERENCIA ENTRE CUENTAS | N126: =VLOOKUP(M126,RECATALOGANDO!B:C,2,0) -> TRANSFERENCIAS | O126: TRANSFERENCIAS
A127: 45439 | B127: =DAY(A127) -> 27 | C127: =MONTH(A127) -> 5 | D127: =YEAR(A127) -> 2024 | E127: =WEEKDAY(A127,2) -> 1 | F127: =WEEKNUM(A127,2) - WEEKNUM(DATE(YEAR(A127),MONTH(A127),1),2) + 1 -> 5 | H127: 800 | I127: BANAMEX | J127: TRANSFERENCIA ENTRE CUENTAS | M127: =VLOOKUP(J127,RECATALOGANDO!A:C,2,0) -> TRANSFERENCIA ENTRE CUENTAS | N127: =VLOOKUP(M127,RECATALOGANDO!B:C,2,0) -> TRANSFERENCIAS | O127: TRANSFERENCIAS
A128: 45440 | B128: =DAY(A128) -> 28 | C128: =MONTH(A128) -> 5 | D128: =YEAR(A128) -> 2024 | E128: =WEEKDAY(A128,2) -> 2 | F128: =WEEKNUM(A128,2) - WEEKNUM(DATE(YEAR(A128),MONTH(A128),1),2) + 1 -> 5 | H128: 500 | I128: BANAMEX | J128: TRANSFERENCIA FAMILIAR | M128: =VLOOKUP(J128,RECATALOGANDO!A:C,2,0) -> TRANSFERENCIA FAMILIAR | N128: =VLOOKUP(M128,RECATALOGANDO!B:C,2,0) -> TRANSFERENCIAS | O128: TRANSFERENCIAS
A129: 45440 | B129: =DAY(A129) -> 28 | C129: =MONTH(A129) -> 5 | D129: =YEAR(A129) -> 2024 | E129: =WEEKDAY(A129,2) -> 2 | F129: =WEEKNUM(A129,2) - WEEKNUM(DATE(YEAR(A129),MONTH(A129),1),2) + 1 -> 5 | H129: 800 | I129: BANAMEX | J129: TRANSFERENCIA ENTRE CUENTAS | M129: =VLOOKUP(J129,RECATALOGANDO!A:C,2,0) -> TRANSFERENCIA ENTRE CUENTAS | N129: =VLOOKUP(M129,RECATALOGANDO!B:C,2,0) -> TRANSFERENCIAS | O129: TRANSFERENCIAS
... A138: 45455 | B138: =DAY(A138) -> 12 | C138: =MONTH(A138) -> 6 | D138: =YEAR(A138) -> 2024 | E138: =WEEKDAY(A138,2) -> 3 | F138: =WEEKNUM(A138,2) - WEEKNUM(DATE(YEAR(A138),MONTH(A138),1),2) + 1 -> 3 | H138: 540 | I138: BANAMEX | J138: TRANSFERENCIA FAMILIAR | M138: =VLOOKUP(J138,RECATALOGANDO!A:C,2,0) -> TRANSFERENCIA FAMILIAR | N138: =VLOOKUP(M138,RECATALOGANDO!B:C,2,0) -> TRANSFERENCIAS | O138: TRANSFERENCIAS
A139: 45457 | B139: =DAY(A139) -> 14 | C139: =MONTH(A139) -> 6 | D139: =YEAR(A139) -> 2024 | E139: =WEEKDAY(A139,2) -> 5 | F139: =WEEKNUM(A139,2) - WEEKNUM(DATE(YEAR(A139),MONTH(A139),1),2) + 1 -> 3 | G139: 1 | H139: 400 | I139: BBVA | J139: TRANSFERENCIA FAMILIAR | M139: =VLOOKUP(J139,RECATALOGANDO!A:C,2,0) -> TRANSFERENCIA FAMILIAR | N139: =VLOOKUP(M139,RECATALOGANDO!B:C,2,0) -> TRANSFERENCIAS | O139: TRANSFERENCIAS
A140: 45457 | B140: =DAY(A140) -> 14 | C140: =MONTH(A140) -> 6 | D140: =YEAR(A140) -> 2024 | E140: =WEEKDAY(A140,2) -> 5 | F140: =WEEKNUM(A140,2) - WEEKNUM(DATE(YEAR(A140),MONTH(A140),1),2) + 1 -> 3 | G140: 1 | H140: 583 | I140: BBVA | J140: TRANSFERENCIA ENTRE CUENTAS | M140: =VLOOKUP(J140,RECATALOGANDO!A:C,2,0) -> TRANSFERENCIA ENTRE CUENTAS | N140: =VLOOKUP(M140,RECATALOGANDO!B:C,2,0) -> TRANSFERENCIAS | O140: TRANSFERENCIAS
A141: 45461 | B141: =DAY(A141) -> 18 | C141: =MONTH(A141) -> 6 | D141: =YEAR(A141) -> 2024 | E141: =WEEKDAY(A141,2) -> 2 | F141: =WEEKNUM(A141,2) - WEEKNUM(DATE(YEAR(A141),MONTH(A141),1),2) + 1 -> 4 | H141: 2000 | I141: BBVA | J141: TRANSFERENCIA ENTRE CUENTAS | M141: =VLOOKUP(J141,RECATALOGANDO!A:C,2,0) -> TRANSFERENCIA ENTRE CUENTAS | N141: =VLOOKUP(M141,RECATALOGANDO!B:C,2,0) -> TRANSFERENCIAS | O141: TRANSFERENCIAS
A142: 45463 | B142: =DAY(A142) -> 20 | C142: =MONTH(A142) -> 6 | D142: =YEAR(A142) -> 2024 | E142: =WEEKDAY(A142,2) -> 4 | F142: =WEEKNUM(A142,2) - WEEKNUM(DATE(YEAR(A142),MONTH(A142),1),2) + 1 -> 4 | H142: 300 | I142: BANAMEX | J142: TRANSFERENCIA FAMILIAR | M142: =VLOOKUP(J142,RECATALOGANDO!A:C,2,0) -> TRANSFERENCIA FAMILIAR | N142: =VLOOKUP(M142,RECATALOGANDO!B:C,2,0) -> TRANSFERENCIAS | O142: TRANSFERENCIAS
A143: 45477 | B143: =DAY(A143) -> 4 | C143: =MONTH(A143) -> 7 | D143: =YEAR(A143) -> 2024 | E143: =WEEKDAY(A143,2) -> 4 | F143: =WEEKNUM(A143,2) - WEEKNUM(DATE(YEAR(A143),MONTH(A143),1),2) + 1 -> 1 | H143: 1000 | I143: BBVA | J143: TRANSFERENCIA ENTRE CUENTAS | M143: =VLOOKUP(J143,RECATALOGANDO!A:C,2,0) -> TRANSFERENCIA ENTRE CUENTAS | N143: =VLOOKUP(M143,RECATALOGANDO!B:C,2,0) -> TRANSFERENCIAS | O143: TRANSFERENCIAS
A144: 45479 | B144: =DAY(A144) -> 6 | C144: =MONTH(A144) -> 7 | D144: =YEAR(A144) -> 2024 | E144: =WEEKDAY(A144,2) -> 6 | F144: =WEEKNUM(A144,2) - WEEKNUM(DATE(YEAR(A144),MONTH(A144),1),2) + 1 -> 1 | H144: 2500 | I144: BBVA | J144: TRANSFERENCIA ENTRE CUENTAS | M144: =VLOOKUP(J144,RECATALOGANDO!A:C,2,0) -> TRANSFERENCIA ENTRE CUENTAS | N144: =VLOOKUP(M144,RECATALOGANDO!B:C,2,0) -> TRANSFERENCIAS | O144: TRANSFERENCIAS
A145: 45505 | B145: =DAY(A145) -> 1 | C145: =MONTH(A145) -> 8 | D145: =YEAR(A145) -> 2024 | E145: =WEEKDAY(A145,2) -> 4 | F145: =WEEKNUM(A145,2) - WEEKNUM(DATE(YEAR(A145),MONTH(A145),1),2) + 1 -> 1 | H145: 500 | I145: BANAMEX | J145: TRANSFERENCIA FAMILIAR | M145: =VLOOKUP(J145,RECATALOGANDO!A:C,2,0) -> TRANSFERENCIA FAMILIAR | N145: =VLOOKUP(M145,RECATALOGANDO!B:C,2,0) -> TRANSFERENCIAS | O145: TRANSFERENCIAS
A146: 45505 | B146: =DAY(A146) -> 1 | C146: =MONTH(A146) -> 8 | D146: =YEAR(A146) -> 2024 | E146: =WEEKDAY(A146,2) -> 4 | F146: =WEEKNUM(A146,2) - WEEKNUM(DATE(YEAR(A146),MONTH(A146),1),2) + 1 -> 1 | H146: 500 | I146: BANAMEX | J146: TRANSFERENCIA FAMILIAR | M146: =VLOOKUP(J146,RECATALOGANDO!A:C,2,0) -> TRANSFERENCIA FAMILIAR | N146: =VLOOKUP(M146,RECATALOGANDO!B:C,2,0) -> TRANSFERENCIAS | O146: TRANSFERENCIAS
A147: 45505 | B147: =DAY(A147) -> 1 | C147: =MONTH(A147) -> 8 | D147: =YEAR(A147) -> 2024 | E147: =WEEKDAY(A147,2) -> 4 | F147: =WEEKNUM(A147,2) - WEEKNUM(DATE(YEAR(A147),MONTH(A147),1),2) + 1 -> 1 | H147: 900 | I147: BANAMEX | J147: ENTRE CUENTAS | M147: =VLOOKUP(J147,RECATALOGANDO!A:C,2,0) -> TRANSFERENCIA ENTRE CUENTAS | N147: =VLOOKUP(M147,RECATALOGANDO!B:C,2,0) -> TRANSFERENCIAS | O147: TRANSFERENCIAS
A148: 45505 | B148: =DAY(A148) -> 1 | C148: =MONTH(A148) -> 8 | D148: =YEAR(A148) -> 2024 | E148: =WEEKDAY(A148,2) -> 4 | F148: =WEEKNUM(A148,2) - WEEKNUM(DATE(YEAR(A148),MONTH(A148),1),2) + 1 -> 1 | H148: 900 | I148: BANAMEX | J148: ENTRE CUENTAS | M148: =VLOOKUP(J148,RECATALOGANDO!A:C,2,0) -> TRANSFERENCIA ENTRE CUENTAS | N148: =VLOOKUP(M148,RECATALOGANDO!B:C,2,0) -> TRANSFERENCIAS | O148: TRANSFERENCIAS
A149: 45506 | B149: =DAY(A149) -> 2 | C149: =MONTH(A149) -> 8 | D149: =YEAR(A149) -> 2024 | E149: =WEEKDAY(A149,2) -> 5 | F149: =WEEKNUM(A149,2) - WEEKNUM(DATE(YEAR(A149),MONTH(A149),1),2) + 1 -> 1 | H149: 300 | I149: BANAMEX | J149: ENTRE CUENTAS | M149: =VLOOKUP(J149,RECATALOGANDO!A:C,2,0) -> TRANSFERENCIA ENTRE CUENTAS | N149: =VLOOKUP(M149,RECATALOGANDO!B:C,2,0) -> TRANSFERENCIAS | O149: TRANSFERENCIAS
A150: 45506 | B150: =DAY(A150) -> 2 | C150: =MONTH(A150) -> 8 | D150: =YEAR(A150) -> 2024 | E150: =WEEKDAY(A150,2) -> 5 | F150: =WEEKNUM(A150,2) - WEEKNUM(DATE(YEAR(A150),MONTH(A150),1),2) + 1 -> 1 | H150: 300 | I150: BANAMEX | J150: ENTRE CUENTAS | M150: =VLOOKUP(J150,RECATALOGANDO!A:C,2,0) -> TRANSFERENCIA ENTRE CUENTAS | N150: =VLOOKUP(M150,RECATALOGANDO!B:C,2,0) -> TRANSFERENCIAS | O150: TRANSFERENCIAS
A151: 45506 | B151: =DAY(A151) -> 2 | C151: =MONTH(A151) -> 8 | D151: =YEAR(A151) -> 2024 | E151: =WEEKDAY(A151,2) -> 5 | F151: =WEEKNUM(A151,2) - WEEKNUM(DATE(YEAR(A151),MONTH(A151),1),2) + 1 -> 1 | H151: 644 | I151: BBVA | J151: ENTRE CUENTAS | M151: =VLOOKUP(J151,RECATALOGANDO!A:C,2,0) -> TRANSFERENCIA ENTRE CUENTAS | N151: =VLOOKUP(M151,RECATALOGANDO!B:C,2,0) -> TRANSFERENCIAS | O151: TRANSFERENCIAS
A152: 45506 | B152: =DAY(A152) -> 2 | C152: =MONTH(A152) -> 8 | D152: =YEAR(A152) -> 2024 | E152: =WEEKDAY(A152,2) -> 5 | F152: =WEEKNUM(A152,2) - WEEKNUM(DATE(YEAR(A152),MONTH(A152),1),2) + 1 -> 1 | H152: 644 | I152: BBVA | J152: ENTRE CUENTAS | M152: =VLOOKUP(J152,RECATALOGANDO!A:C,2,0) -> TRANSFERENCIA ENTRE CUENTAS | N152: =VLOOKUP(M152,RECATALOGANDO!B:C,2,0) -> TRANSFERENCIAS | O152: TRANSFERENCIAS
... A162: 45589 | B162: =DAY(A162) -> 24 | C162: =MONTH(A162) -> 10 | D162: =YEAR(A162) -> 2024 | E162: =WEEKDAY(A162,2) -> 4 | F162: =WEEKNUM(A162,2) - WEEKNUM(DATE(YEAR(A162),MONTH(A162),1),2) + 1 -> 4 | H162: 700 | I162: BANAMEX | J162: ENTRE CUENTAS | M162: =VLOOKUP(J162,RECATALOGANDO!A:C,2,0) -> TRANSFERENCIA ENTRE CUENTAS | N162: =VLOOKUP(M162,RECATALOGANDO!B:C,2,0) -> TRANSFERENCIAS | O162: TRANSFERENCIAS
A163: 45611 | B163: =DAY(A163) -> 15 | C163: =MONTH(A163) -> 11 | D163: =YEAR(A163) -> 2024 | E163: =WEEKDAY(A163,2) -> 5 | F163: =WEEKNUM(A163,2) - WEEKNUM(DATE(YEAR(A163),MONTH(A163),1),2) + 1 -> 3 | G163: 1 | H163: 2000 | I163: BANAMEX | J163: TRANSFERENCIA ENTRE CUENTAS | M163: =VLOOKUP(J163,RECATALOGANDO!A:C,2,0) -> TRANSFERENCIA ENTRE CUENTAS | N163: =VLOOKUP(M163,RECATALOGANDO!B:C,2,0) -> TRANSFERENCIAS | O163: TRANSFERENCIAS
...

Sheet RECATALOGANDO
A1: CONCEPTO | B1: CONCEPTO 2 | C1: AGRUPADO | H1: CONCEPTO 2 | I1: AGRUPADO
A2: ABONO POR REEMBOLSO POR CARGO NO RECONOCIDO | B2: REEMBOLSO | C2: DINERO DEVUELTO A ORIGEN | H2: REEMBOLSO | I2: DINERO DEVUELTO A ORIGEN
A3: APLICACIÓN DE VACUNAS | B3: VENTA DE MEDICAMENTO | C3: VENTA DE PRODUCTO | H3: VENTA DE MEDICAMENTO | I3: VENTA DE PRODUCTO
A4: DEPOSITO EQUIVOCADO QUE FUE REEMBOLSADO | B4: REEMBOLSO | C4: DINERO DEVUELTO A ORIGEN | H4: TRANSFERENCIA FAMILIAR | I4: TRANSFERENCIAS
A5: DEPÓSITO EQUIVOCADO Y DEVUELTO | B5: REEMBOLSO | C5: DINERO DEVUELTO A ORIGEN | H5: PENSION ALIMENTICIA | I5: PENSION
A6: DEPOSITO FAMILIAR | B6: TRANSFERENCIA FAMILIAR | C6: TRANSFERENCIAS | H6: DEPÓSITO PRESTAMO | I6: PRESTAMO
A7: DEPÓSITO FAMILIAR | B7: TRANSFERENCIA FAMILIAR | C7: TRANSFERENCIAS | H7: REEMBOLSO | I7: DINERO DEVUELTO
A8: DEPOSITO PENSION ALIMENTICIA | B8: PENSION ALIMENTICIA | C8: PENSION | H8: DONATIVO | I8: DONATIVO
A9: DEPÓSITO PRESTAMO | B9: DEPÓSITO PRESTAMO | C9: PRESTAMO | H9: TRANSFERENCIA ENTRE CUENTAS | I9: TRANSFERENCIAS
A10: DEVOLUCIÓN SPEI | B10: REEMBOLSO | C10: DINERO DEVUELTO | H10: HONORARIOS MEDICOS | I10: VENTA DE SERVICIO
A11: DONATIVO | B11: DONATIVO | C11: DONATIVO | H11: HONORARIOS QUIRURGICOS | I11: VENTA DE SERVICIO
A12: ENTRE CUENTAS | B12: TRANSFERENCIA ENTRE CUENTAS | C12: TRANSFERENCIAS | H12: VENTA DE ALIMENTO | I12: VENTA DE PRODUCTO
... A20: PAGO SERVICIO DE PENSIÓN | B20: SERVICIO DE PENSION | C20: VENTA DE SERVICIO | H20: VENTA DE ACCESORIOS | I20: VENTA DE PRODUCTO
A21: PENSIÓN ALIMENTICIA | B21: PENSION ALIMENTICIA | C21: PENSION
A22: PRESTAMO BANCARIO | B22: PRESTAMO BANCARIO | C22: PRESTAMO
A23: REEMBOLSO | B23: REEMBOLSO | C23: DINERO DEVUELTO A ORIGEN
A24: REEMBOLSO POR DEPOSITO EQUIVOCADO | B24: REEMBOLSO | C24: DINERO DEVUELTO A ORIGEN
A25: SERVCIO DE PENSIÓN | B25: SERVICIO DE PENSION | C25: VENTA DE SERVICIO
A26: SERVICIO DE CREMACIÓN | B26: SERVICIO DE CREMACION | C26: VENTA DE SERVICIO
A27: SERVICIO DE GROOMING | B27: SERVICIO DE GROOMING | C27: VENTA DE SERVICIO
A28: SERVICIO DE HOSPITALIZACION | B28: SERVICIO DE HOSPITALIZACION | C28: VENTA DE SERVICIO
A29: SERVICIO DE IMAGEN | B29: SERVICIO DE IMAGEN | C29: VENTA DE SERVICIO
A30: SERVICIO DE IMAGENOLOGIA | B30: SERVICIO DE IMAGEN | C30: VENTA DE SERVICIO
A31: SERVICIO DE INCINERACIÓN | B31: SERVICIO DE CREMACION | C31: VENTA DE SERVICIO
A32: SERVICIO DE LABORATORIO | B32: SERVICIO DE LABORATORIO | C32: VENTA DE SERVICIO
... A56: VENTA MEDICAMENTO | B56: VENTA DE MEDICAMENTO | C56: VENTA DE PRODUCTO

Sheet CATS
A1: ID | B1: DESCRIPCION | F1: ID_ | G1: DESCRIPCION | I1: ID | J1: DESCRIPCION
A2: 1 | B2: HONORARIOS MEDICOS | C2: MEDICOS | F2: 1 | G2: BBVA | I2: 1 | J2: VENTAS
A3: 2 | B3: HONORARIOS QUIRURGICOS | C3: QUIRURGICOS | F3: 2 | G3: BANAMEX | I3: 2 | J3: TRANSFERENCIA
A4: 3 | B4: SERVICIO DE CREMACIÓN | C4: CREMACIÓN | F4: 3 | G4: BANORTE | I4: 3 | J4: HONORARIOS
A5: 4 | B5: SERVICIO DE GROOMING | C5: GROOMING | I5: 4 | J5: SERVICIOS
A6: 5 | B6: SERVICIO DE LABORATORIO | C6: LABORATORIO
A7: 6 | B7: SERVICIO DE PENSIÓN | C7: PENSIÓN
A8: 7 | B8: TRANSFERENCIA ENTRE CUENTAS | C8: CUENTAS
A9: 8 | B9: TRANSFERENCIA FAMILIARES | C9: FAMILIARES
A10: 9 | B10: VENTA DE ALIMENTO | C10: ALIMENTO
A11: 10 | B11: VENTA DE MEDICAMENTO | C11: MEDICAMENTO
